parts_made/control_unit.v
module control_unit(
    input clk,
    input reset,
    input [31:0] instruction,
    input zero_flag,
    input overflow,
    input div_zero,
    
    // Instruction fields
    output reg [5:0] opcode,
    output reg [4:0] rs,
    output reg [4:0] rt,
    output reg [4:0] rd,
    output reg [4:0] shamt,
    output reg [5:0] funct,
    output reg [15:0] immediate,
    output reg [25:0] address,
    
    // ALU controls
    output reg [3:0] alu_control,
    output reg alu_zero,
    output reg alu_overflow,
    
    // Control signals
    output reg reg_dst,
    output reg jump,
    output reg branch,
    output reg mem_read,
    output reg mem_to_reg,
    output reg [3:0] alu_op,
    output reg mem_write,
    output reg alu_src,
    output reg reg_write,
    
    // Load/Store size controls
    output reg [1:0] load_size_control,
    output reg [1:0] store_size_control,
    
    // PC controls
    output reg pc_write,
    output reg pc_write_cond,
    output reg [1:0] pc_source,
    
    // Shift amount control
    output reg [1:0] shift_amt_selector,
    
    // State output
    output [4:0] current_state
);

    // VARIABLES
    reg [4:0] state;     // 5 bits para representar o estado atual
    reg [4:0] counter;   // 5 bits para representar o clk atual em um dado estado
    
    // Instruction field extraction
    always @(*) begin
        opcode = instruction[31:26];
        rs = instruction[25:21];
        rt = instruction[20:16];
        rd = instruction[15:11];
        shamt = instruction[10:6];
        funct = instruction[5:0];
        immediate = instruction[15:0];
        address = instruction[25:0];
    end
    
    // Assign current state to output
    assign current_state = state;

    // STATE PARAMETERS
    parameter ST_RESET          = 5'b00000;
    parameter ST_FETCH          = 5'b00001;
    parameter ST_DECODE         = 5'b00010;
    parameter ST_ADD            = 5'b00011;
    parameter ST_AND            = 5'b00100;
    parameter ST_DIV            = 5'b00101;
    parameter ST_MULT           = 5'b00110;
    parameter ST_JR             = 5'b00111;
    parameter ST_MFHI           = 5'b01000;
    parameter ST_MFLO           = 5'b01001;
    parameter ST_SLL            = 5'b01010;
    parameter ST_SLT            = 5'b01011;
    parameter ST_SRA            = 5'b01100;
    parameter ST_SUB            = 5'b01101;
    parameter ST_XCHG           = 5'b01110;
    parameter ST_ADDI           = 5'b01111;
    parameter ST_BEQ            = 5'b10000;
    parameter ST_BNE            = 5'b10001;
    parameter ST_SLLM           = 5'b10010;
    parameter ST_LB             = 5'b10011;
    parameter ST_LUI            = 5'b10100;
    parameter ST_LW             = 5'b10101;
    parameter ST_SB             = 5'b10110;
    parameter ST_SW             = 5'b10111;
    parameter ST_J              = 5'b11000;
    parameter ST_JAL            = 5'b11001;
    parameter ST_OVERFLOW       = 5'b11010;
    parameter ST_OPCODE404      = 5'b11011;
    parameter ST_DIV0           = 5'b11100;

    // Opcodes (instruction type)
    parameter OP_TYPE_R = 6'b000000;
    parameter OP_ADDI   = 6'b001000;
    parameter OP_BEQ    = 6'b000100;
    parameter OP_BNE    = 6'b000101;
    parameter OP_SLLM   = 6'b000001;
    parameter OP_LB     = 6'b100000;
    parameter OP_LUI    = 6'b001111;
    parameter OP_LW     = 6'b100011;
    parameter OP_SB     = 6'b101000;
    parameter OP_SW     = 6'b101011;
    parameter OP_J      = 6'b000010;
    parameter OP_JAL    = 6'b000011;

    // Function codes for R-type instructions
    parameter FUNCT_ADD  = 6'b100000;
    parameter FUNCT_AND  = 6'b100100;
    parameter FUNCT_DIV  = 6'b011010;
    parameter FUNCT_MULT = 6'b011000;
    parameter FUNCT_JR   = 6'b001000;
    parameter FUNCT_MFHI = 6'b010000;
    parameter FUNCT_MFLO = 6'b010010;
    parameter FUNCT_SLL  = 6'b000000;
    parameter FUNCT_SLT  = 6'b101010;
    parameter FUNCT_SRA  = 6'b000011;
    parameter FUNCT_SUB  = 6'b100010;
    parameter FUNCT_XCHG = 6'b000101;

    // Inicialização
    initial begin
        state = ST_RESET;
    end

    // Main state machine
    always @(posedge clk) begin
        if (reset) begin
            state = ST_RESET;
            counter = 5'b00000;
        end else begin
            case (state)
                ST_RESET: handle_reset_state();
                ST_FETCH: handle_fetch_state();
                ST_DECODE: handle_decode_state();
                ST_OVERFLOW: handle_overflow_state();
                ST_OPCODE404: handle_opcode404_state();
                ST_DIV0: handle_div0_state();
                ST_ADD: handle_add_state();
                ST_AND: handle_and_state();
                ST_DIV: handle_div_state();
                ST_MULT: handle_mult_state();
                ST_JR: handle_jr_state();
                ST_MFHI: handle_mfhi_state();
                ST_MFLO: handle_mflo_state();
                ST_SLL: handle_sll_state();
                ST_SLT: handle_slt_state();
                ST_SRA: handle_sra_state();
                ST_SUB: handle_sub_state();
                ST_XCHG: handle_xchg_state();
                ST_ADDI: handle_addi_state();
                ST_BEQ: handle_beq_state();
                ST_BNE: handle_bne_state();
                ST_SLLM: handle_sllm_state();
                ST_LB: handle_lb_state();
                ST_LUI: handle_lui_state();
                ST_LW: handle_lw_state();
                ST_SB: handle_sb_state();
                ST_SW: handle_sw_state();
                ST_J: handle_j_state();
                ST_JAL: handle_jal_state();
                default: state = ST_OPCODE404;
            endcase
        end
    end

    // TASKS
    task reset_control_signals;
        begin
            // Control signals
            reg_dst = 1'b0;
            jump = 1'b0;
            branch = 1'b0;
            mem_read = 1'b0;
            mem_to_reg = 1'b0;
            alu_op = 4'b0000;
            mem_write = 1'b0;
            alu_src = 1'b0;
            reg_write = 1'b0;
            
            // Load/Store size controls
            load_size_control = 2'b00;
            store_size_control = 2'b00;
            
            // PC controls
            pc_write = 1'b0;
            pc_write_cond = 1'b0;
            pc_source = 2'b00;
            
            // Shift amount control
            shift_amt_selector = 2'b00;
            
            // ALU controls
            alu_control = 4'b0000;
            alu_zero = 1'b0;
            alu_overflow = 1'b0;
        end
    endtask

    // Tasks para cada estado
    task handle_reset_state;
        begin
            reset_control_signals();
            state = ST_FETCH;
            counter = 5'b00000;
        end
    endtask

    task handle_fetch_state;
        begin
            // Reset todos os sinais de controle no FETCH
            reset_control_signals();
            
            // Configurar sinais específicos do FETCH
            mem_read = 1'b1;
            pc_write = 1'b1;
            pc_source = 2'b00; // PC + 4
            
            state = ST_DECODE;
            counter = 5'b00000;
        end
    endtask

    task handle_decode_state;
        begin
            counter = 5'b00000;
            decode_instruction();
        end
    endtask

    task decode_instruction;
        begin
            case (opcode)
                OP_TYPE_R: begin
                    case (funct)
                        FUNCT_ADD:  state = ST_ADD;
                        FUNCT_AND:  state = ST_AND;
                        FUNCT_DIV:  state = ST_DIV;
                        FUNCT_MULT: state = ST_MULT;
                        FUNCT_JR:   state = ST_JR;
                        FUNCT_MFHI: state = ST_MFHI;
                        FUNCT_MFLO: state = ST_MFLO;
                        FUNCT_SLL:  state = ST_SLL;
                        FUNCT_SLT:  state = ST_SLT;
                        FUNCT_SRA:  state = ST_SRA;
                        FUNCT_SUB:  state = ST_SUB;
                        FUNCT_XCHG: state = ST_XCHG;
                        default:    state = ST_OPCODE404;
                    endcase
                end
                OP_ADDI:    state = ST_ADDI;
                OP_BEQ:     state = ST_BEQ;
                OP_BNE:     state = ST_BNE;
                OP_SLLM:    state = ST_SLLM;
                OP_LB:      state = ST_LB;
                OP_LUI:     state = ST_LUI;
                OP_LW:      state = ST_LW;
                OP_SB:      state = ST_SB;
                OP_SW:      state = ST_SW;
                OP_J:       state = ST_J;
                OP_JAL:     state = ST_JAL;
                default:    state = ST_OPCODE404;
            endcase
        end
    endtask

    // R-type instruction tasks
    task handle_add_state;
        begin
            reg_dst = 1'b1;
            alu_src = 1'b0; // Use register
            alu_op = 4'b0010; // ADD
            alu_control = 4'b0010; // ADD
            reg_write = 1'b1;
            if (overflow) state = ST_OVERFLOW;
            else state = ST_FETCH;
        end
    endtask

    task handle_and_state;
        begin
            reg_dst = 1'b1;
            alu_src = 1'b0; // Use register
            alu_op = 4'b0001; // AND
            alu_control = 4'b0001; // AND
            reg_write = 1'b1;
            state = ST_FETCH;
        end
    endtask

    task handle_div_state;
        begin
            alu_src = 1'b0; // Use register
            alu_op = 4'b1001; // DIV
            alu_control = 4'b1001; // DIV
            if (div_zero) state = ST_DIV0;
            else state = ST_FETCH;
        end
    endtask

    task handle_mult_state;
        begin
            alu_src = 1'b0; // Use register
            alu_op = 4'b1010; // MULT
            alu_control = 4'b1010; // MULT
            state = ST_FETCH;
        end
    endtask

    task handle_jr_state;
        begin
            pc_write = 1'b1;
            pc_source = 2'b10; // Register
            state = ST_FETCH;
        end
    endtask

    task handle_mfhi_state;
        begin
            reg_dst = 1'b1;
            alu_src = 1'b0; // Use register
            alu_op = 4'b1100; // MFHI
            alu_control = 4'b1100; // MFHI
            reg_write = 1'b1;
            state = ST_FETCH;
        end
    endtask

    task handle_mflo_state;
        begin
            reg_dst = 1'b1;
            alu_src = 1'b0; // Use register
            alu_op = 4'b1101; // MFLO
            alu_control = 4'b1101; // MFLO
            reg_write = 1'b1;
            state = ST_FETCH;
        end
    endtask

    task handle_sll_state;
        begin
            reg_dst = 1'b1;
            alu_src = 1'b0; // Use register
            alu_op = 4'b0100; // SLL
            alu_control = 4'b0100; // SLL
            reg_write = 1'b1;
            shift_amt_selector = 2'b11; // Use shamt from instruction
            state = ST_FETCH;
        end
    endtask

    task handle_slt_state;
        begin
            reg_dst = 1'b1;
            alu_src = 1'b0; // Use register
            alu_op = 4'b0111; // SLT
            alu_control = 4'b0111; // SLT
            reg_write = 1'b1;
            state = ST_FETCH;
        end
    endtask

    task handle_sra_state;
        begin
            reg_dst = 1'b1;
            alu_src = 1'b0; // Use register
            alu_op = 4'b0101; // SRA
            alu_control = 4'b0101; // SRA
            reg_write = 1'b1;
            shift_amt_selector = 2'b11; // Use shamt from instruction
            state = ST_FETCH;
        end
    endtask

    task handle_sub_state;
        begin
            reg_dst = 1'b1;
            alu_src = 1'b0; // Use register
            alu_op = 4'b0110; // SUB
            alu_control = 4'b0110; // SUB
            reg_write = 1'b1;
            if (overflow) state = ST_OVERFLOW;
            else state = ST_FETCH;
        end
    endtask

    task handle_xchg_state;
        begin
            reg_dst = 1'b1;
            alu_src = 1'b0; // Use register
            alu_op = 4'b1011; // XCHG
            alu_control = 4'b1011; // XCHG
            reg_write = 1'b1;
            state = ST_FETCH;
        end
    endtask

    // I-type instruction tasks
    task handle_addi_state;
        begin
            alu_src = 1'b1; // Immediate
            alu_op = 4'b0010; // ADD
            reg_write = 1'b1;
            if (overflow) state = ST_OVERFLOW;
            else state = ST_FETCH;
        end
    endtask

    task handle_beq_state;
        begin
            branch = 1'b1;
            alu_op = 4'b0110; // SUB for comparison
            pc_write_cond = 1'b1;
            pc_source = 2'b01; // Branch target
            state = ST_FETCH;
        end
    endtask

    task handle_bne_state;
        begin
            branch = 1'b1;
            alu_op = 4'b0110; // SUB for comparison
            pc_write_cond = 1'b1;
            pc_source = 2'b01; // Branch target
            state = ST_FETCH;
        end
    endtask

    task handle_sllm_state;
        begin
            alu_src = 1'b1; // Immediate
            alu_op = 4'b0100; // SLL
            reg_write = 1'b1;
            state = ST_FETCH;
        end
    endtask

    task handle_lb_state;
        begin
            alu_src = 1'b1; // Immediate
            alu_op = 4'b0010; // ADD for address calculation
            mem_read = 1'b1;
            mem_to_reg = 1'b1;
            reg_write = 1'b1;
            load_size_control = 2'b00; // Load byte - 1 byte
            state = ST_FETCH;
        end
    endtask

    task handle_lui_state;
        begin
            alu_src = 1'b1; // Immediate
            alu_op = 4'b1000; // LUI
            reg_write = 1'b1;
            state = ST_FETCH;
        end
    endtask

    task handle_lw_state;
        begin
            alu_src = 1'b1; // Immediate
            alu_op = 4'b0010; // ADD for address calculation
            mem_read = 1'b1;
            mem_to_reg = 1'b1;
            reg_write = 1'b1;
            load_size_control = 2'b10; // Load word - 4 bytes
            state = ST_FETCH;
        end
    endtask

    task handle_sb_state;
        begin
            alu_src = 1'b1; // Immediate
            alu_op = 4'b0010; // ADD for address calculation
            mem_write = 1'b1;
            store_size_control = 2'b00; // Store byte - 1 byte
            state = ST_FETCH;
        end
    endtask

    task handle_sw_state;
        begin
            alu_src = 1'b1; // Immediate
            alu_op = 4'b0010; // ADD for address calculation
            mem_write = 1'b1;
            store_size_control = 2'b10; // Store word - 4 bytes
            state = ST_FETCH;
        end
    endtask

    // J-type instruction tasks
    task handle_j_state;
        begin
            jump = 1'b1;
            pc_write = 1'b1;
            pc_source = 2'b11; // Jump target
            state = ST_FETCH;
        end
    endtask

    task handle_jal_state;
        begin
            jump = 1'b1;
            pc_write = 1'b1;
            pc_source = 2'b11; // Jump target
            reg_write = 1'b1; // Write return address to $ra
            state = ST_FETCH;
        end
    endtask

    // Exception handling tasks
    task handle_overflow_state;
        begin
            pc_write = 1'b1;
            pc_source = 2'b11; // Exception handler address
            state = ST_FETCH;
        end
    endtask

    task handle_opcode404_state;
        begin
            pc_write = 1'b1;
            pc_source = 2'b11; // Exception handler address
            state = ST_FETCH;
        end
    endtask

    task handle_div0_state;
        begin
            pc_write = 1'b1;
            pc_source = 2'b11; // Exception handler address
            state = ST_FETCH;
        end
    endtask

endmodule

test_control_signals.v
module test_control_signals;
    reg clk;
    reg reset;
    reg [31:0] instruction;
    reg zero_flag;
    reg overflow;
    reg div_zero;
    
    // Control signals outputs
    wire [5:0] opcode;
    wire [4:0] rs, rt, rd, shamt;
    wire [5:0] funct;
    wire [15:0] immediate;
    wire [25:0] address;
    wire [3:0] alu_control;
    wire alu_zero, alu_overflow;
    wire reg_dst, jump, branch, mem_read, mem_to_reg;
    wire [3:0] alu_op;
    wire mem_write, alu_src, reg_write;
    wire [1:0] load_size_control, store_size_control;
    wire pc_write, pc_write_cond;
    wire [1:0] pc_source;
    wire [1:0] shift_amt_selector;
    wire [4:0] current_state;
    
    // Instantiate control unit
    control_unit uut (
        .clk(clk),
        .reset(reset),
        .instruction(instruction),
        .zero_flag(zero_flag),
        .overflow(overflow),
        .div_zero(div_zero),
        .opcode(opcode),
        .rs(rs),
        .rt(rt),
        .rd(rd),
        .shamt(shamt),
        .funct(funct),
        .immediate(immediate),
        .address(address),
        .alu_control(alu_control),
        .alu_zero(alu_zero),
        .alu_overflow(alu_overflow),
        .reg_dst(reg_dst),
        .jump(jump),
        .branch(branch),
        .mem_read(mem_read),
        .mem_to_reg(mem_to_reg),
        .alu_op(alu_op),
        .mem_write(mem_write),
        .alu_src(alu_src),
        .reg_write(reg_write),
        .load_size_control(load_size_control),
        .store_size_control(store_size_control),
        .pc_write(pc_write),
        .pc_write_cond(pc_write_cond),
        .pc_source(pc_source),
        .shift_amt_selector(shift_amt_selector),
        .current_state(current_state)
    );
    
    // Clock generation
    initial begin
        clk = 0;
        forever #5 clk = ~clk;
    end
    
    // Test sequence
    initial begin
        $dumpfile("test_control_signals.vcd");
        $dumpvars(0, test_control_signals);
        
        // Initialize
        reset = 1;
        instruction = 32'h00000000;
        zero_flag = 0;
        overflow = 0;
        div_zero = 0;
        
        // Reset
        #10 reset = 0;
        
        // Test ADD instruction (R-type): add $t0, $t1, $t2
        // opcode=000000, rs=01001, rt=01010, rd=01000, shamt=00000, funct=100000
        #10 instruction = 32'b000000_01001_01010_01000_00000_100000;
        
        // Wait for instruction to be processed
        #30;
        
        // Test SLL instruction (R-type): sll $t0, $t1, 2
        // opcode=000000, rs=00000, rt=01001, rd=01000, shamt=00010, funct=000000
        instruction = 32'b000000_00000_01001_01000_00010_000000;
        
        // Wait for instruction to be processed
        #30;
        
        // Test ADDI instruction (I-type): addi $t0, $t1, 100
        // opcode=001000, rs=01001, rt=01000, immediate=0000000001100100
        instruction = 32'b001000_01001_01000_0000000001100100;
        
        // Wait for instruction to be processed
        #30;
        
        $display("Test completed");
        $finish;
    end
    
    // Monitor signals
    always @(posedge clk) begin
        $display("Time=%0t State=%d Instruction=%h", $time, current_state, instruction);
        $display("  reg_dst=%b alu_op=%b reg_write=%b alu_src=%b", reg_dst, alu_op, reg_write, alu_src);
        $display("  shift_amt_selector=%b mem_read=%b mem_write=%b", shift_amt_selector, mem_read, mem_write);
        $display("");
    end
    
endmodule

test_control_signals.vcd
$date
	Sun Jul 13 03:30:33 2025
$end
$version
	Icarus Verilog
$end
$timescale
	1s
$end
$scope module test_control_signals $end
$var wire 2 ! store_size_control [1:0] $end
$var wire 2 " shift_amt_selector [1:0] $end
$var wire 5 # shamt [4:0] $end
$var wire 5 $ rt [4:0] $end
$var wire 5 % rs [4:0] $end
$var wire 1 & reg_write $end
$var wire 1 ' reg_dst $end
$var wire 5 ( rd [4:0] $end
$var wire 1 ) pc_write_cond $end
$var wire 1 * pc_write $end
$var wire 2 + pc_source [1:0] $end
$var wire 6 , opcode [5:0] $end
$var wire 1 - mem_write $end
$var wire 1 . mem_to_reg $end
$var wire 1 / mem_read $end
$var wire 2 0 load_size_control [1:0] $end
$var wire 1 1 jump $end
$var wire 16 2 immediate [15:0] $end
$var wire 6 3 funct [5:0] $end
$var wire 5 4 current_state [4:0] $end
$var wire 1 5 branch $end
$var wire 1 6 alu_zero $end
$var wire 1 7 alu_src $end
$var wire 1 8 alu_overflow $end
$var wire 4 9 alu_op [3:0] $end
$var wire 4 : alu_control [3:0] $end
$var wire 26 ; address [25:0] $end
$var reg 1 < clk $end
$var reg 1 = div_zero $end
$var reg 32 > instruction [31:0] $end
$var reg 1 ? overflow $end
$var reg 1 @ reset $end
$var reg 1 A zero_flag $end
$scope module uut $end
$var wire 1 < clk $end
$var wire 5 B current_state [4:0] $end
$var wire 1 = div_zero $end
$var wire 32 C instruction [31:0] $end
$var wire 1 ? overflow $end
$var wire 1 @ reset $end
$var wire 1 A zero_flag $end
$var parameter 6 D FUNCT_ADD $end
$var parameter 6 E FUNCT_AND $end
$var parameter 6 F FUNCT_DIV $end
$var parameter 6 G FUNCT_JR $end
$var parameter 6 H FUNCT_MFHI $end
$var parameter 6 I FUNCT_MFLO $end
$var parameter 6 J FUNCT_MULT $end
$var parameter 6 K FUNCT_SLL $end
$var parameter 6 L FUNCT_SLT $end
$var parameter 6 M FUNCT_SRA $end
$var parameter 6 N FUNCT_SUB $end
$var parameter 6 O FUNCT_XCHG $end
$var parameter 6 P OP_ADDI $end
$var parameter 6 Q OP_BEQ $end
$var parameter 6 R OP_BNE $end
$var parameter 6 S OP_J $end
$var parameter 6 T OP_JAL $end
$var parameter 6 U OP_LB $end
$var parameter 6 V OP_LUI $end
$var parameter 6 W OP_LW $end
$var parameter 6 X OP_SB $end
$var parameter 6 Y OP_SLLM $end
$var parameter 6 Z OP_SW $end
$var parameter 6 [ OP_TYPE_R $end
$var parameter 5 \ ST_ADD $end
$var parameter 5 ] ST_ADDI $end
$var parameter 5 ^ ST_AND $end
$var parameter 5 _ ST_BEQ $end
$var parameter 5 ` ST_BNE $end
$var parameter 5 a ST_DECODE $end
$var parameter 5 b ST_DIV $end
$var parameter 5 c ST_DIV0 $end
$var parameter 5 d ST_FETCH $end
$var parameter 5 e ST_J $end
$var parameter 5 f ST_JAL $end
$var parameter 5 g ST_JR $end
$var parameter 5 h ST_LB $end
$var parameter 5 i ST_LUI $end
$var parameter 5 j ST_LW $end
$var parameter 5 k ST_MFHI $end
$var parameter 5 l ST_MFLO $end
$var parameter 5 m ST_MULT $end
$var parameter 5 n ST_OPCODE404 $end
$var parameter 5 o ST_OVERFLOW $end
$var parameter 5 p ST_RESET $end
$var parameter 5 q ST_SB $end
$var parameter 5 r ST_SLL $end
$var parameter 5 s ST_SLLM $end
$var parameter 5 t ST_SLT $end
$var parameter 5 u ST_SRA $end
$var parameter 5 v ST_SUB $end
$var parameter 5 w ST_SW $end
$var parameter 5 x ST_XCHG $end
$var reg 26 y address [25:0] $end
$var reg 4 z alu_control [3:0] $end
$var reg 4 { alu_op [3:0] $end
$var reg 1 8 alu_overflow $end
$var reg 1 7 alu_src $end
$var reg 1 6 alu_zero $end
$var reg 1 5 branch $end
$var reg 5 | counter [4:0] $end
$var reg 6 } funct [5:0] $end
$var reg 16 ~ immediate [15:0] $end
$var reg 1 1 jump $end
$var reg 2 !" load_size_control [1:0] $end
$var reg 1 / mem_read $end
$var reg 1 . mem_to_reg $end
$var reg 1 - mem_write $end
$var reg 6 "" opcode [5:0] $end
$var reg 2 #" pc_source [1:0] $end
$var reg 1 * pc_write $end
$var reg 1 ) pc_write_cond $end
$var reg 5 $" rd [4:0] $end
$var reg 1 ' reg_dst $end
$var reg 1 & reg_write $end
$var reg 5 %" rs [4:0] $end
$var reg 5 &" rt [4:0] $end
$var reg 5 '" shamt [4:0] $end
$var reg 2 (" shift_amt_selector [1:0] $end
$var reg 5 )" state [4:0] $end
$var reg 2 *" store_size_control [1:0] $end
$scope task decode_instruction $end
$upscope $end
$scope task handle_add_state $end
$upscope $end
$scope task handle_addi_state $end
$upscope $end
$scope task handle_and_state $end
$upscope $end
$scope task handle_beq_state $end
$upscope $end
$scope task handle_bne_state $end
$upscope $end
$scope task handle_decode_state $end
$upscope $end
$scope task handle_div0_state $end
$upscope $end
$scope task handle_div_state $end
$upscope $end
$scope task handle_fetch_state $end
$upscope $end
$scope task handle_j_state $end
$upscope $end
$scope task handle_jal_state $end
$upscope $end
$scope task handle_jr_state $end
$upscope $end
$scope task handle_lb_state $end
$upscope $end
$scope task handle_lui_state $end
$upscope $end
$scope task handle_lw_state $end
$upscope $end
$scope task handle_mfhi_state $end
$upscope $end
$scope task handle_mflo_state $end
$upscope $end
$scope task handle_mult_state $end
$upscope $end
$scope task handle_opcode404_state $end
$upscope $end
$scope task handle_overflow_state $end
$upscope $end
$scope task handle_reset_state $end
$upscope $end
$scope task handle_sb_state $end
$upscope $end
$scope task handle_sll_state $end
$upscope $end
$scope task handle_sllm_state $end
$upscope $end
$scope task handle_slt_state $end
$upscope $end
$scope task handle_sra_state $end
$upscope $end
$scope task handle_sub_state $end
$upscope $end
$scope task handle_sw_state $end
$upscope $end
$scope task handle_xchg_state $end
$upscope $end
$scope task reset_control_signals $end
$upscope $end
$upscope $end
$upscope $end
$enddefinitions $end
$comment Show the parameter values. $end
$dumpall
b1110 x
b10111 w
b1101 v
b1100 u
b1011 t
b10010 s
b1010 r
b10110 q
b0 p
b11010 o
b11011 n
b110 m
b1001 l
b1000 k
b10101 j
b10100 i
b10011 h
b111 g
b11001 f
b11000 e
b1 d
b11100 c
b101 b
b10 a
b10001 `
b10000 _
b100 ^
b1111 ]
b11 \
b0 [
b101011 Z
b1 Y
b101000 X
b100011 W
b1111 V
b100000 U
b11 T
b10 S
b101 R
b100 Q
b1000 P
b101 O
b100010 N
b11 M
b101010 L
b0 K
b11000 J
b10010 I
b10000 H
b1000 G
b11010 F
b100100 E
b100000 D
$end
#0
$dumpvars
bx *"
b0 )"
bx ("
b0 '"
b0 &"
b0 %"
b0 $"
bx #"
b0 ""
bx !"
b0 ~
b0 }
bx |
bx {
b0 z
b0 y
b0 C
b0 B
0A
1@
0?
b0 >
0=
0<
b0 ;
b0 :
bx 9
x8
x7
x6
x5
b0 4
b0 3
b0 2
x1
bx 0
x/
x.
x-
b0 ,
bx +
x*
x)
b0 (
x'
x&
b0 %
b0 $
b0 #
bx "
bx !
$end
#5
b0 |
1<
#10
0<
0@
#15
b1 4
b1 B
b1 )"
08
06
b0 "
b0 ("
b0 +
b0 #"
0)
0*
b0 !
b0 *"
b0 0
b0 !"
0&
07
0-
b0 9
b0 {
0.
0/
05
01
0'
1<
#20
b1001010100100000000100000 ;
b1001010100100000000100000 y
b100000000100000 2
b100000000100000 ~
b100000 3
b100000 }
b1000 (
b1000 $"
b1010 $
b1010 &"
b1001 %
b1001 %"
0<
b1001010100100000000100000 >
b1001010100100000000100000 C
#25
b10 4
b10 B
b10 )"
1*
1/
1<
#30
0<
#35
b11 4
b11 B
b11 )"
1<
#40
0<
#45
b10 :
b10 z
b1 4
b1 B
b1 )"
1&
b10 9
b10 {
1'
1<
#50
b10010100000010000000 ;
b10010100000010000000 y
b100000010000000 2
b100000010000000 ~
b0 3
b0 }
b10 #
b10 '"
b1001 $
b1001 &"
b0 %
b0 %"
0<
b10010100000010000000 >
b10010100000010000000 C
#55
b10 4
b10 B
b10 )"
b0 :
b0 z
1*
0&
b0 9
b0 {
1/
0'
1<
#60
0<
#65
b1010 4
b1010 B
b1010 )"
1<
#70
0<
#75
b100 :
b100 z
b1 4
b1 B
b1 )"
b11 "
b11 ("
1&
b100 9
b100 {
1'
1<
#80
b1001010000000000001100100 ;
b1001010000000000001100100 y
b1100100 2
b1100100 ~
b100100 3
b100100 }
b1 #
b1 '"
b0 (
b0 $"
b1000 $
b1000 &"
b1001 %
b1001 %"
b1000 ,
b1000 ""
0<
b100001001010000000000001100100 >
b100001001010000000000001100100 C
#85
b10 4
b10 B
b10 )"
b0 :
b0 z
b0 "
b0 ("
1*
0&
b0 9
b0 {
1/
0'
1<
#90
0<
#95
b1111 4
b1111 B
b1111 )"
1<
#100
0<
#105
b10 :
b10 z
b1 4
b1 B
b1 )"
1&
b10 9
b10 {
17
1<
