parts_made/ss.v
// Unidade de SS (Store Size)
// Entrada:
// RegBOut(32 bits): valor novo a ser salvo na memória
// RegMDROut(32 bits): valor antigo na memória
// RegSSControl(2 bits): seleção de como irá salvar o valor
// Saída: SSControlOut(32 bits): valor a ser armazenado na memória

module ss (
    input  wire [1:0]  RegSSControl,    // Seleção: 00=byte, 01=halfword, 10=word
    input  wire [31:0] RegBOut,         // Valor novo a ser salvo na memória
    input  wire [31:0] RegMDROut,       // Valor antigo na memória
    output reg  [31:0] SSControlOut     // Valor a ser armazenado na memória
);

    always @(*) begin
        case (RegSSControl)
            2'b00: SSControlOut = {RegMDROut[31:8], RegBOut[7:0]};    // Store byte - preserva 3 bytes antigos
            2'b01: SSControlOut = {RegMDROut[31:16], RegBOut[15:0]};  // Store halfword - preserva 2 bytes antigos
            2'b10: SSControlOut = RegBOut;                            // Store word - substitui palavra completa
            default: SSControlOut = RegMDROut;                        // Caso padrão - mantém valor antigo
        endcase
    end

endmodule

parts_made/ls.v
// Unidade de LS (Load Size)
// Entrada:
// RegMDROut(32 bits): valor obtido da memória
// LSControl(2 bits): seleção de como irá ser salvo o valor no banco de registradores
// Saída: LSControlOut(32 bits): valor a ser armazenado no banco de registradores

module ls(
    input  wire [1:0] LSControl,        // Seleção: 00=byte, 01=halfword, 10=word
    input  wire [31:0] RegMDROut,       // Valor obtido da memória
    output reg  [31:0] LSControlOut     // Valor a ser armazenado no banco de registradores
);

    always @(*) begin
        case (LSControl)
            2'b00: LSControlOut = {24'b0, RegMDROut[7:0]};   // Load byte - 1 byte, resto com 0
            2'b01: LSControlOut = {16'b0, RegMDROut[15:0]};  // Load halfword - 2 bytes, resto com 0
            2'b10: LSControlOut = RegMDROut;                 // Load word - 4 bytes completos
            default: LSControlOut = 32'b0;                   // Caso padrão
        endcase
    end

endmodule

parts_made/test/test_ls_ss_units.v
// Teste das unidades LS e SS adaptadas conforme especificação
// Este teste verifica se as unidades LS e SS estão funcionando corretamente
// com os novos sinais de controle de 2 bits

`timescale 1ns / 1ps

module test_ls_ss_units;

    // Sinais para teste da unidade LS
    reg [1:0] ls_control;
    reg [31:0] reg_mdr_out;
    wire [31:0] ls_control_out;
    
    // Sinais para teste da unidade SS
    reg [1:0] ss_control;
    reg [31:0] reg_b_out;
    reg [31:0] reg_mdr_out_ss;
    wire [31:0] ss_control_out;
    
    // Instanciação da unidade LS
    ls uut_ls (
        .LSControl(ls_control),
        .RegMDROut(reg_mdr_out),
        .LSControlOut(ls_control_out)
    );
    
    // Instanciação da unidade SS
    ss uut_ss (
        .RegSSControl(ss_control),
        .RegBOut(reg_b_out),
        .RegMDROut(reg_mdr_out_ss),
        .SSControlOut(ss_control_out)
    );
    
    // Configuração para dump VCD
    initial begin
        $dumpfile("test_ls_ss_units.vcd");
        $dumpvars(0, test_ls_ss_units);
    end
    
    // Testes principais
    initial begin
        $display("=== TESTE DAS UNIDADES LS E SS ADAPTADAS ===");
        
        // === TESTE DA UNIDADE LS ===
        $display("\n=== TESTE DA UNIDADE LS (Load Size) ===");
        
        // Valor de teste na memória
        reg_mdr_out = 32'hAABBCCDD;
        
        // Teste Load Byte (LSControl = 00)
        ls_control = 2'b00;
        #10;
        $display("Load Byte (LSControl=00):");
        $display("  RegMDROut: 0x%h", reg_mdr_out);
        $display("  LSControlOut: 0x%h (esperado: 0x000000DD)", ls_control_out);
        
        // Teste Load Halfword (LSControl = 01)
        ls_control = 2'b01;
        #10;
        $display("Load Halfword (LSControl=01):");
        $display("  RegMDROut: 0x%h", reg_mdr_out);
        $display("  LSControlOut: 0x%h (esperado: 0x0000CCDD)", ls_control_out);
        
        // Teste Load Word (LSControl = 10)
        ls_control = 2'b10;
        #10;
        $display("Load Word (LSControl=10):");
        $display("  RegMDROut: 0x%h", reg_mdr_out);
        $display("  LSControlOut: 0x%h (esperado: 0xAABBCCDD)", ls_control_out);
        
        // === TESTE DA UNIDADE SS ===
        $display("\n=== TESTE DA UNIDADE SS (Store Size) ===");
        
        // Valores de teste
        reg_b_out = 32'h12345678;      // Novo valor a ser salvo
        reg_mdr_out_ss = 32'hAABBCCDD; // Valor antigo na memória
        
        // Teste Store Byte (SSControl = 00)
        ss_control = 2'b00;
        #10;
        $display("Store Byte (SSControl=00):");
        $display("  RegBOut: 0x%h", reg_b_out);
        $display("  RegMDROut: 0x%h", reg_mdr_out_ss);
        $display("  SSControlOut: 0x%h (esperado: 0xAABBCC78)", ss_control_out);
        
        // Teste Store Halfword (SSControl = 01)
        ss_control = 2'b01;
        #10;
        $display("Store Halfword (SSControl=01):");
        $display("  RegBOut: 0x%h", reg_b_out);
        $display("  RegMDROut: 0x%h", reg_mdr_out_ss);
        $display("  SSControlOut: 0x%h (esperado: 0xAABB5678)", ss_control_out);
        
        // Teste Store Word (SSControl = 10)
        ss_control = 2'b10;
        #10;
        $display("Store Word (SSControl=10):");
        $display("  RegBOut: 0x%h", reg_b_out);
        $display("  RegMDROut: 0x%h", reg_mdr_out_ss);
        $display("  SSControlOut: 0x%h (esperado: 0x12345678)", ss_control_out);
        
        // === TESTE DE CASOS EXTREMOS ===
        $display("\n=== TESTE DE CASOS EXTREMOS ===");
        
        // Teste com valores zero
        reg_mdr_out = 32'h00000000;
        reg_b_out = 32'h00000000;
        reg_mdr_out_ss = 32'hFFFFFFFF;
        
        ls_control = 2'b00; // Load byte de zero
        ss_control = 2'b00; // Store byte de zero
        #10;
        $display("Load Byte de zero: 0x%h (esperado: 0x00000000)", ls_control_out);
        $display("Store Byte de zero: 0x%h (esperado: 0xFFFFFF00)", ss_control_out);
        
        // Teste com valores máximos
        reg_mdr_out = 32'hFFFFFFFF;
        reg_b_out = 32'hFFFFFFFF;
        reg_mdr_out_ss = 32'h00000000;
        
        ls_control = 2'b10; // Load word máximo
        ss_control = 2'b10; // Store word máximo
        #10;
        $display("Load Word máximo: 0x%h (esperado: 0xFFFFFFFF)", ls_control_out);
        $display("Store Word máximo: 0x%h (esperado: 0xFFFFFFFF)", ss_control_out);
        
        $display("\n=== TESTE DAS UNIDADES LS E SS CONCLUÍDO ===");
        $finish;
    end
    
endmodule

parts_made/test/test_ls_ss_units.vcd
$date
	Sat Jul 12 22:27:43 2025
$end
$version
	Icarus Verilog
$end
$timescale
	1ps
$end
$scope module test_ls_ss_units $end
$var wire 32 ! ss_control_out [31:0] $end
$var wire 32 " ls_control_out [31:0] $end
$var reg 2 # ls_control [1:0] $end
$var reg 32 $ reg_b_out [31:0] $end
$var reg 32 % reg_mdr_out [31:0] $end
$var reg 32 & reg_mdr_out_ss [31:0] $end
$var reg 2 ' ss_control [1:0] $end
$scope module uut_ls $end
$var wire 2 ( LSControl [1:0] $end
$var wire 32 ) RegMDROut [31:0] $end
$var reg 32 * LSControlOut [31:0] $end
$upscope $end
$scope module uut_ss $end
$var wire 32 + RegBOut [31:0] $end
$var wire 32 , RegMDROut [31:0] $end
$var wire 2 - RegSSControl [1:0] $end
$var reg 32 . SSControlOut [31:0] $end
$upscope $end
$upscope $end
$enddefinitions $end
$comment Show the parameter values. $end
$dumpall
$end
#0
$dumpvars
bx .
bx -
bx ,
bx +
b11011101 *
b10101010101110111100110011011101 )
b0 (
bx '
bx &
b10101010101110111100110011011101 %
bx $
b0 #
b11011101 "
bx !
$end
#10000
b1100110011011101 "
b1100110011011101 *
b1 #
b1 (
#20000
b10101010101110111100110011011101 "
b10101010101110111100110011011101 *
b10 #
b10 (
#30000
b10101010101110111100110001111000 !
b10101010101110111100110001111000 .
b0 '
b0 -
b10101010101110111100110011011101 &
b10101010101110111100110011011101 ,
b10010001101000101011001111000 $
b10010001101000101011001111000 +
#40000
b10101010101110110101011001111000 !
b10101010101110110101011001111000 .
b1 '
b1 -
#50000
b10010001101000101011001111000 !
b10010001101000101011001111000 .
b10 '
b10 -
#60000
b11111111111111111111111100000000 !
b11111111111111111111111100000000 .
b0 "
b0 *
b0 '
b0 -
b0 #
b0 (
b11111111111111111111111111111111 &
b11111111111111111111111111111111 ,
b0 $
b0 +
b0 %
b0 )
#70000
b11111111111111111111111111111111 !
b11111111111111111111111111111111 .
b11111111111111111111111111111111 "
b11111111111111111111111111111111 *
b10 '
b10 -
b10 #
b10 (
b0 &
b0 ,
b11111111111111111111111111111111 $
b11111111111111111111111111111111 +
b11111111111111111111111111111111 %
b11111111111111111111111111111111 )
