parts_made/control_unit.v
module control_unit(
    input clk,
    input reset,
    input [31:0] instruction,
    input zero_flag,
    input overflow,
    input div_zero,
    
    // Instruction fields
    output reg [5:0] opcode,
    output reg [4:0] rs,
    output reg [4:0] rt,
    output reg [4:0] rd,
    output reg [4:0] shamt,
    output reg [5:0] funct,
    output reg [15:0] immediate,
    output reg [25:0] address,
    
    // ALU controls
    output reg [3:0] alu_control,
    output reg alu_zero,
    output reg alu_overflow,
    
    // Control signals
    output reg reg_dst,
    output reg jump,
    output reg branch,
    output reg mem_read,
    output reg mem_to_reg,
    output reg [3:0] alu_op,
    output reg mem_write,
    output reg alu_src,
    output reg reg_write,
    
    // Load/Store size controls
    output reg [1:0] load_size_control,
    output reg [1:0] store_size_control,
    
    // PC controls
    output reg pc_write,
    output reg pc_write_cond,
    output reg [1:0] pc_source,
    
    // Shift amount control
    output reg [1:0] shift_amt_selector,
    
    // State output
    output [4:0] current_state
);

    // VARIABLES
    reg [4:0] state;     // 5 bits para representar o estado atual
    reg [4:0] counter;   // 5 bits para representar o clk atual em um dado estado
    
    // Instruction field extraction
    always @(*) begin
        opcode = instruction[31:26];
        rs = instruction[25:21];
        rt = instruction[20:16];
        rd = instruction[15:11];
        shamt = instruction[10:6];
        funct = instruction[5:0];
        immediate = instruction[15:0];
        address = instruction[25:0];
    end
    
    // Assign current state to output
    assign current_state = state;

    // STATE PARAMETERS
    parameter ST_RESET          = 5'b00000;
    parameter ST_FETCH          = 5'b00001;
    parameter ST_DECODE         = 5'b00010;
    parameter ST_ADD            = 5'b00011;
    parameter ST_AND            = 5'b00100;
    parameter ST_DIV            = 5'b00101;
    parameter ST_MULT           = 5'b00110;
    parameter ST_JR             = 5'b00111;
    parameter ST_MFHI           = 5'b01000;
    parameter ST_MFLO           = 5'b01001;
    parameter ST_SLL            = 5'b01010;
    parameter ST_SLT            = 5'b01011;
    parameter ST_SRA            = 5'b01100;
    parameter ST_SUB            = 5'b01101;
    parameter ST_XCHG           = 5'b01110;
    parameter ST_ADDI           = 5'b01111;
    parameter ST_BEQ            = 5'b10000;
    parameter ST_BNE            = 5'b10001;
    parameter ST_SLLM           = 5'b10010;
    parameter ST_LB             = 5'b10011;
    parameter ST_LUI            = 5'b10100;
    parameter ST_LW             = 5'b10101;
    parameter ST_SB             = 5'b10110;
    parameter ST_SW             = 5'b10111;
    parameter ST_J              = 5'b11000;
    parameter ST_JAL            = 5'b11001;
    parameter ST_OVERFLOW       = 5'b11010;
    parameter ST_OPCODE404      = 5'b11011;
    parameter ST_DIV0           = 5'b11100;

    // Opcodes (instruction type)
    parameter OP_TYPE_R = 6'b000000;
    parameter OP_ADDI   = 6'b001000;
    parameter OP_BEQ    = 6'b000100;
    parameter OP_BNE    = 6'b000101;
    parameter OP_SLLM   = 6'b000001;
    parameter OP_LB     = 6'b100000;
    parameter OP_LUI    = 6'b001111;
    parameter OP_LW     = 6'b100011;
    parameter OP_SB     = 6'b101000;
    parameter OP_SW     = 6'b101011;
    parameter OP_J      = 6'b000010;
    parameter OP_JAL    = 6'b000011;

    // Function codes for R-type instructions
    parameter FUNCT_ADD  = 6'b100000;
    parameter FUNCT_AND  = 6'b100100;
    parameter FUNCT_DIV  = 6'b011010;
    parameter FUNCT_MULT = 6'b011000;
    parameter FUNCT_JR   = 6'b001000;
    parameter FUNCT_MFHI = 6'b010000;
    parameter FUNCT_MFLO = 6'b010010;
    parameter FUNCT_SLL  = 6'b000000;
    parameter FUNCT_SLT  = 6'b101010;
    parameter FUNCT_SRA  = 6'b000011;
    parameter FUNCT_SUB  = 6'b100010;
    parameter FUNCT_XCHG = 6'b000101;

    // Inicialização
    initial begin
        state = ST_RESET;
    end

    // Main state machine
    always @(posedge clk) begin
        if (reset) begin
            state = ST_RESET;
            counter = 5'b00000;
        end else begin
            case (state)
                ST_RESET: handle_reset_state();
                ST_FETCH: handle_fetch_state();
                ST_DECODE: handle_decode_state();
                ST_OVERFLOW: handle_overflow_state();
                ST_OPCODE404: handle_opcode404_state();
                ST_DIV0: handle_div0_state();
                ST_ADD: handle_add_state();
                ST_AND: handle_and_state();
                ST_DIV: handle_div_state();
                ST_MULT: handle_mult_state();
                ST_JR: handle_jr_state();
                ST_MFHI: handle_mfhi_state();
                ST_MFLO: handle_mflo_state();
                ST_SLL: handle_sll_state();
                ST_SLT: handle_slt_state();
                ST_SRA: handle_sra_state();
                ST_SUB: handle_sub_state();
                ST_XCHG: handle_xchg_state();
                ST_ADDI: handle_addi_state();
                ST_BEQ: handle_beq_state();
                ST_BNE: handle_bne_state();
                ST_SLLM: handle_sllm_state();
                ST_LB: handle_lb_state();
                ST_LUI: handle_lui_state();
                ST_LW: handle_lw_state();
                ST_SB: handle_sb_state();
                ST_SW: handle_sw_state();
                ST_J: handle_j_state();
                ST_JAL: handle_jal_state();
                default: state = ST_OPCODE404;
            endcase
        end
    end

    // TASKS
    task reset_control_signals;
        begin
            // Control signals
            reg_dst = 1'b0;
            jump = 1'b0;
            branch = 1'b0;
            mem_read = 1'b0;
            mem_to_reg = 1'b0;
            alu_op = 4'b0000;
            mem_write = 1'b0;
            alu_src = 1'b0;
            reg_write = 1'b0;
            
            // Load/Store size controls
            load_size_control = 2'b00;
            store_size_control = 2'b00;
            
            // PC controls
            pc_write = 1'b0;
            pc_write_cond = 1'b0;
            pc_source = 2'b00;
            
            // Shift amount control
            shift_amt_selector = 2'b00;
            
            // ALU controls
            alu_control = 4'b0000;
            alu_zero = 1'b0;
            alu_overflow = 1'b0;
        end
    endtask

    // Tasks para cada estado
    task handle_reset_state;
        begin
            reset_control_signals();
            state = ST_FETCH;
            counter = 5'b00000;
        end
    endtask

    task handle_fetch_state;
        begin
            // Reset todos os sinais de controle no FETCH
            reset_control_signals();
            
            // Configurar sinais específicos do FETCH
            mem_read = 1'b1;
            pc_write = 1'b1;
            pc_source = 2'b00; // PC + 4
            
            state = ST_DECODE;
            counter = 5'b00000;
        end
    endtask

    task handle_decode_state;
        begin
            counter = 5'b00000;
            decode_instruction();
        end
    endtask

    task decode_instruction;
        begin
            case (opcode)
                OP_TYPE_R: begin
                    case (funct)
                        FUNCT_ADD:  state = ST_ADD;
                        FUNCT_AND:  state = ST_AND;
                        FUNCT_DIV:  state = ST_DIV;
                        FUNCT_MULT: state = ST_MULT;
                        FUNCT_JR:   state = ST_JR;
                        FUNCT_MFHI: state = ST_MFHI;
                        FUNCT_MFLO: state = ST_MFLO;
                        FUNCT_SLL:  state = ST_SLL;
                        FUNCT_SLT:  state = ST_SLT;
                        FUNCT_SRA:  state = ST_SRA;
                        FUNCT_SUB:  state = ST_SUB;
                        FUNCT_XCHG: state = ST_XCHG;
                        default:    state = ST_OPCODE404;
                    endcase
                end
                OP_ADDI:    state = ST_ADDI;
                OP_BEQ:     state = ST_BEQ;
                OP_BNE:     state = ST_BNE;
                OP_SLLM:    state = ST_SLLM;
                OP_LB:      state = ST_LB;
                OP_LUI:     state = ST_LUI;
                OP_LW:      state = ST_LW;
                OP_SB:      state = ST_SB;
                OP_SW:      state = ST_SW;
                OP_J:       state = ST_J;
                OP_JAL:     state = ST_JAL;
                default:    state = ST_OPCODE404;
            endcase
        end
    endtask

    // R-type instruction tasks
    task handle_add_state;
        begin
            reg_dst = 1'b1;
            alu_op = 4'b0010; // ADD
            alu_control = 4'b0010; // ADD
            reg_write = 1'b1;
            if (overflow) state = ST_OVERFLOW;
            else state = ST_FETCH;
        end
    endtask

    task handle_and_state;
        begin
            reg_dst = 1'b1;
            alu_op = 4'b0001; // AND
            alu_control = 4'b0001; // AND
            reg_write = 1'b1;
            state = ST_FETCH;
        end
    endtask

    task handle_div_state;
        begin
            alu_op = 4'b1001; // DIV
            alu_control = 4'b1001; // DIV
            if (div_zero) state = ST_DIV0;
            else state = ST_FETCH;
        end
    endtask

    task handle_mult_state;
        begin
            alu_op = 4'b1010; // MULT
            alu_control = 4'b1010; // MULT
            state = ST_FETCH;
        end
    endtask

    task handle_jr_state;
        begin
            pc_write = 1'b1;
            pc_source = 2'b10; // Register
            state = ST_FETCH;
        end
    endtask

    task handle_mfhi_state;
        begin
            reg_dst = 1'b1;
            alu_op = 4'b1100; // MFHI
            alu_control = 4'b1100; // MFHI
            reg_write = 1'b1;
            state = ST_FETCH;
        end
    endtask

    task handle_mflo_state;
        begin
            reg_dst = 1'b1;
            alu_op = 4'b1101; // MFLO
            alu_control = 4'b1101; // MFLO
            reg_write = 1'b1;
            state = ST_FETCH;
        end
    endtask

    task handle_sll_state;
        begin
            reg_dst = 1'b1;
            alu_op = 4'b0100; // SLL
            alu_control = 4'b0100; // SLL
            reg_write = 1'b1;
            shift_amt_selector = 2'b11; // Use shamt from instruction
            state = ST_FETCH;
        end
    endtask

    task handle_slt_state;
        begin
            reg_dst = 1'b1;
            alu_op = 4'b0111; // SLT
            alu_control = 4'b0111; // SLT
            reg_write = 1'b1;
            state = ST_FETCH;
        end
    endtask

    task handle_sra_state;
        begin
            reg_dst = 1'b1;
            alu_op = 4'b0101; // SRA
            alu_control = 4'b0101; // SRA
            reg_write = 1'b1;
            shift_amt_selector = 2'b11; // Use shamt from instruction
            state = ST_FETCH;
        end
    endtask

    task handle_sub_state;
        begin
            reg_dst = 1'b1;
            alu_op = 4'b0110; // SUB
            alu_control = 4'b0110; // SUB
            reg_write = 1'b1;
            if (overflow) state = ST_OVERFLOW;
            else state = ST_FETCH;
        end
    endtask

    task handle_xchg_state;
        begin
            reg_dst = 1'b1;
            alu_op = 4'b1011; // XCHG
            alu_control = 4'b1011; // XCHG
            reg_write = 1'b1;
            state = ST_FETCH;
        end
    endtask

    // I-type instruction tasks
    task handle_addi_state;
        begin
            alu_src = 1'b1; // Immediate
            alu_op = 4'b0010; // ADD
            reg_write = 1'b1;
            if (overflow) state = ST_OVERFLOW;
            else state = ST_FETCH;
        end
    endtask

    task handle_beq_state;
        begin
            branch = 1'b1;
            alu_op = 4'b0110; // SUB for comparison
            pc_write_cond = 1'b1;
            pc_source = 2'b01; // Branch target
            state = ST_FETCH;
        end
    endtask

    task handle_bne_state;
        begin
            branch = 1'b1;
            alu_op = 4'b0110; // SUB for comparison
            pc_write_cond = 1'b1;
            pc_source = 2'b01; // Branch target
            state = ST_FETCH;
        end
    endtask

    task handle_sllm_state;
        begin
            alu_src = 1'b1; // Immediate
            alu_op = 4'b0100; // SLL
            reg_write = 1'b1;
            state = ST_FETCH;
        end
    endtask

    task handle_lb_state;
        begin
            alu_src = 1'b1; // Immediate
            alu_op = 4'b0010; // ADD for address calculation
            mem_read = 1'b1;
            mem_to_reg = 1'b1;
            reg_write = 1'b1;
            load_size_control = 2'b00; // Load byte - 1 byte
            state = ST_FETCH;
        end
    endtask

    task handle_lui_state;
        begin
            alu_src = 1'b1; // Immediate
            alu_op = 4'b1000; // LUI
            reg_write = 1'b1;
            state = ST_FETCH;
        end
    endtask

    task handle_lw_state;
        begin
            alu_src = 1'b1; // Immediate
            alu_op = 4'b0010; // ADD for address calculation
            mem_read = 1'b1;
            mem_to_reg = 1'b1;
            reg_write = 1'b1;
            load_size_control = 2'b10; // Load word - 4 bytes
            state = ST_FETCH;
        end
    endtask

    task handle_sb_state;
        begin
            alu_src = 1'b1; // Immediate
            alu_op = 4'b0010; // ADD for address calculation
            mem_write = 1'b1;
            store_size_control = 2'b00; // Store byte - 1 byte
            state = ST_FETCH;
        end
    endtask

    task handle_sw_state;
        begin
            alu_src = 1'b1; // Immediate
            alu_op = 4'b0010; // ADD for address calculation
            mem_write = 1'b1;
            store_size_control = 2'b10; // Store word - 4 bytes
            state = ST_FETCH;
        end
    endtask

    // J-type instruction tasks
    task handle_j_state;
        begin
            jump = 1'b1;
            pc_write = 1'b1;
            pc_source = 2'b11; // Jump target
            state = ST_FETCH;
        end
    endtask

    task handle_jal_state;
        begin
            jump = 1'b1;
            pc_write = 1'b1;
            pc_source = 2'b11; // Jump target
            reg_write = 1'b1; // Write return address to $ra
            state = ST_FETCH;
        end
    endtask

    // Exception handling tasks
    task handle_overflow_state;
        begin
            pc_write = 1'b1;
            pc_source = 2'b11; // Exception handler address
            state = ST_FETCH;
        end
    endtask

    task handle_opcode404_state;
        begin
            pc_write = 1'b1;
            pc_source = 2'b11; // Exception handler address
            state = ST_FETCH;
        end
    endtask

    task handle_div0_state;
        begin
            pc_write = 1'b1;
            pc_source = 2'b11; // Exception handler address
            state = ST_FETCH;
        end
    endtask

endmodule

parts_made/test/I-type/test_i_type.v
`timescale 1ns / 1ps

module test_i_type;

    // Sinais
    reg clk;
    reg reset;
    reg [31:0] instruction;
    
    // Saídas da control_unit
    wire reg_dst;
    wire alu_src;
    wire [3:0] alu_op;
    wire [3:0] alu_control;
    wire reg_write;
    wire pc_write;
    wire [1:0] pc_source;
    wire branch;
    wire pc_write_cond;
    wire [1:0] shift_amt_selector;
    wire mem_read;
    wire mem_to_reg;
    wire [1:0] load_size_control;
    wire mem_write;
    wire [1:0] store_size_control;
    wire [4:0] current_state;
    
    // Instância da control_unit
    control_unit uut (
        .clk(clk),
        .reset(reset),
        .instruction(instruction),
        .reg_dst(reg_dst),
        .alu_src(alu_src),
        .alu_op(alu_op),
        .alu_control(alu_control),
        .reg_write(reg_write),
        .pc_write(pc_write),
        .pc_source(pc_source),
        .branch(branch),
        .pc_write_cond(pc_write_cond),
        .shift_amt_selector(shift_amt_selector),
        .mem_read(mem_read),
        .mem_to_reg(mem_to_reg),
        .load_size_control(load_size_control),
        .mem_write(mem_write),
        .store_size_control(store_size_control),
        .current_state(current_state)
    );
    
    // Clock
    initial begin
        clk = 0;
        forever #5 clk = ~clk;
    end
    
    // Reset
    task reset_system;
        begin
            reset = 1;
            #20;
            reset = 0;
            #10;
        end
    endtask
    
    // Executar instrução
    task exec_instr(input [31:0] instr);
        begin
            instruction = instr;
            repeat(5) @(posedge clk);
        end
    endtask
    
    initial begin
        $dumpfile("test_i_type.vcd");
        $dumpvars(0, test_i_type);
        
        reset_system();
        
        // ADDI
        $display("ADDI");
        exec_instr(32'h2001000F); // addi $1, $zero, 15
        exec_instr(32'h20220019); // addi $2, $1, 25  
        exec_instr(32'h2043FFF6); // addi $3, $2, -10
        
        // BEQ, BNE
        $display("BEQ, BNE");
        exec_instr(32'h20010005); // addi $1, $zero, 5
        exec_instr(32'h20020005); // addi $2, $zero, 5
        exec_instr(32'h10220003); // beq $1, $2, iguais
        exec_instr(32'h200303E7); // addi $3, $zero, 999
        exec_instr(32'h2001000A); // addi $1, $zero, 10
        exec_instr(32'h14220002); // bne $1, $2, diferentes
        exec_instr(32'h20040378); // addi $4, $zero, 888
        exec_instr(32'h2002000A); // addi $2, $zero, 10
        exec_instr(32'h14220002); // bne $1, $2, erro
        exec_instr(32'h20050064); // addi $5, $zero, 100
        exec_instr(32'h20060309); // addi $6, $zero, 777
        
        // LUI
        $display("LUI");
        exec_instr(32'h3C010001); // lui $1, 1
        exec_instr(32'h3C020007); // lui $2, 7
        exec_instr(32'h3C0300FF); // lui $3, 255
        exec_instr(32'h20640200); // addi $4, $3, 512
        
        // SW, LW, SB, LB
        $display("SW, LW, SB, LB");
        exec_instr(32'h3C0100C8); // lui $1, 200
        exec_instr(32'h20210096); // addi $1, $1, 150
        exec_instr(32'h2021004B); // addi $1, $1, 75
        exec_instr(32'hAC010064); // sw $1, 100($zero)
        exec_instr(32'h8C020064); // lw $2, 100($zero)
        exec_instr(32'h80030064); // lb $3, 100($zero)
        exec_instr(32'h80040065); // lb $4, 101($zero)
        
        exec_instr(32'hAC0100C8); // sw $1, 200($zero)
        exec_instr(32'hA00100D2); // sb $1, 210($zero)
        exec_instr(32'h8C0200C8); // lw $2, 200($zero)
        exec_instr(32'h8C0300D2); // lw $3, 210($zero)
        exec_instr(32'h20050033); // addi $5, $zero, 51
        exec_instr(32'hA00500C8); // sb $5, 200($zero)
        exec_instr(32'h8C0600C8); // lw $6, 200($zero)
        
        // SLLM
        $display("SLLM");
        exec_instr(32'h20010005); // addi $1, $zero, 5
        exec_instr(32'h20020003); // addi $2, $zero, 3
        exec_instr(32'hAC020032); // sw $2, 50($zero)
        exec_instr(32'h1C030032); // sllm $3, 50($zero)
        exec_instr(32'h20040007); // addi $4, $zero, 7
        exec_instr(32'h20050004); // addi $5, $zero, 4
        exec_instr(32'hAC05003C); // sw $5, 60($zero)
        exec_instr(32'h1C06003C); // sllm $6, 60($zero)
        
        $display("Testes concluidos");
        $finish;
    end
    
endmodule

parts_made/test/I-type/test_i_type.vcd
$date
	Mon Jul 14 01:19:05 2025
$end
$version
	Icarus Verilog
$end
$timescale
	1ps
$end
$scope module test_i_type $end
$var wire 2 ! store_size_control [1:0] $end
$var wire 2 " shift_amt_selector [1:0] $end
$var wire 1 # reg_write $end
$var wire 1 $ reg_dst $end
$var wire 1 % pc_write_cond $end
$var wire 1 & pc_write $end
$var wire 2 ' pc_source [1:0] $end
$var wire 1 ( mem_write $end
$var wire 1 ) mem_to_reg $end
$var wire 1 * mem_read $end
$var wire 2 + load_size_control [1:0] $end
$var wire 5 , current_state [4:0] $end
$var wire 1 - branch $end
$var wire 1 . alu_src $end
$var wire 4 / alu_op [3:0] $end
$var wire 4 0 alu_control [3:0] $end
$var reg 1 1 clk $end
$var reg 32 2 instruction [31:0] $end
$var reg 1 3 reset $end
$scope module uut $end
$var wire 1 1 clk $end
$var wire 5 4 current_state [4:0] $end
$var wire 1 5 div_zero $end
$var wire 32 6 instruction [31:0] $end
$var wire 1 7 overflow $end
$var wire 1 3 reset $end
$var wire 1 8 zero_flag $end
$var parameter 6 9 FUNCT_ADD $end
$var parameter 6 : FUNCT_AND $end
$var parameter 6 ; FUNCT_DIV $end
$var parameter 6 < FUNCT_JR $end
$var parameter 6 = FUNCT_MFHI $end
$var parameter 6 > FUNCT_MFLO $end
$var parameter 6 ? FUNCT_MULT $end
$var parameter 6 @ FUNCT_SLL $end
$var parameter 6 A FUNCT_SLT $end
$var parameter 6 B FUNCT_SRA $end
$var parameter 6 C FUNCT_SUB $end
$var parameter 6 D FUNCT_XCHG $end
$var parameter 6 E OP_ADDI $end
$var parameter 6 F OP_BEQ $end
$var parameter 6 G OP_BNE $end
$var parameter 6 H OP_J $end
$var parameter 6 I OP_JAL $end
$var parameter 6 J OP_LB $end
$var parameter 6 K OP_LUI $end
$var parameter 6 L OP_LW $end
$var parameter 6 M OP_SB $end
$var parameter 6 N OP_SLLM $end
$var parameter 6 O OP_SW $end
$var parameter 6 P OP_TYPE_R $end
$var parameter 5 Q ST_ADD $end
$var parameter 5 R ST_ADDI $end
$var parameter 5 S ST_AND $end
$var parameter 5 T ST_BEQ $end
$var parameter 5 U ST_BNE $end
$var parameter 5 V ST_DECODE $end
$var parameter 5 W ST_DIV $end
$var parameter 5 X ST_DIV0 $end
$var parameter 5 Y ST_FETCH $end
$var parameter 5 Z ST_J $end
$var parameter 5 [ ST_JAL $end
$var parameter 5 \ ST_JR $end
$var parameter 5 ] ST_LB $end
$var parameter 5 ^ ST_LUI $end
$var parameter 5 _ ST_LW $end
$var parameter 5 ` ST_MFHI $end
$var parameter 5 a ST_MFLO $end
$var parameter 5 b ST_MULT $end
$var parameter 5 c ST_OPCODE404 $end
$var parameter 5 d ST_OVERFLOW $end
$var parameter 5 e ST_RESET $end
$var parameter 5 f ST_SB $end
$var parameter 5 g ST_SLL $end
$var parameter 5 h ST_SLLM $end
$var parameter 5 i ST_SLT $end
$var parameter 5 j ST_SRA $end
$var parameter 5 k ST_SUB $end
$var parameter 5 l ST_SW $end
$var parameter 5 m ST_XCHG $end
$var reg 26 n address [25:0] $end
$var reg 4 o alu_control [3:0] $end
$var reg 4 p alu_op [3:0] $end
$var reg 1 q alu_overflow $end
$var reg 1 . alu_src $end
$var reg 1 r alu_zero $end
$var reg 1 - branch $end
$var reg 5 s counter [4:0] $end
$var reg 6 t funct [5:0] $end
$var reg 16 u immediate [15:0] $end
$var reg 1 v jump $end
$var reg 2 w load_size_control [1:0] $end
$var reg 1 * mem_read $end
$var reg 1 ) mem_to_reg $end
$var reg 1 ( mem_write $end
$var reg 6 x opcode [5:0] $end
$var reg 2 y pc_source [1:0] $end
$var reg 1 & pc_write $end
$var reg 1 % pc_write_cond $end
$var reg 5 z rd [4:0] $end
$var reg 1 $ reg_dst $end
$var reg 1 # reg_write $end
$var reg 5 { rs [4:0] $end
$var reg 5 | rt [4:0] $end
$var reg 5 } shamt [4:0] $end
$var reg 2 ~ shift_amt_selector [1:0] $end
$var reg 5 !" state [4:0] $end
$var reg 2 "" store_size_control [1:0] $end
$scope task decode_instruction $end
$upscope $end
$scope task handle_add_state $end
$upscope $end
$scope task handle_addi_state $end
$upscope $end
$scope task handle_and_state $end
$upscope $end
$scope task handle_beq_state $end
$upscope $end
$scope task handle_bne_state $end
$upscope $end
$scope task handle_decode_state $end
$upscope $end
$scope task handle_div0_state $end
$upscope $end
$scope task handle_div_state $end
$upscope $end
$scope task handle_fetch_state $end
$upscope $end
$scope task handle_j_state $end
$upscope $end
$scope task handle_jal_state $end
$upscope $end
$scope task handle_jr_state $end
$upscope $end
$scope task handle_lb_state $end
$upscope $end
$scope task handle_lui_state $end
$upscope $end
$scope task handle_lw_state $end
$upscope $end
$scope task handle_mfhi_state $end
$upscope $end
$scope task handle_mflo_state $end
$upscope $end
$scope task handle_mult_state $end
$upscope $end
$scope task handle_opcode404_state $end
$upscope $end
$scope task handle_overflow_state $end
$upscope $end
$scope task handle_reset_state $end
$upscope $end
$scope task handle_sb_state $end
$upscope $end
$scope task handle_sll_state $end
$upscope $end
$scope task handle_sllm_state $end
$upscope $end
$scope task handle_slt_state $end
$upscope $end
$scope task handle_sra_state $end
$upscope $end
$scope task handle_sub_state $end
$upscope $end
$scope task handle_sw_state $end
$upscope $end
$scope task handle_xchg_state $end
$upscope $end
$scope task reset_control_signals $end
$upscope $end
$upscope $end
$scope task exec_instr $end
$var reg 32 #" instr [31:0] $end
$upscope $end
$scope task reset_system $end
$upscope $end
$upscope $end
$enddefinitions $end
$comment Show the parameter values. $end
$dumpall
b1110 m
b10111 l
b1101 k
b1100 j
b1011 i
b10010 h
b1010 g
b10110 f
b0 e
b11010 d
b11011 c
b110 b
b1001 a
b1000 `
b10101 _
b10100 ^
b10011 ]
b111 \
b11001 [
b11000 Z
b1 Y
b11100 X
b101 W
b10 V
b10001 U
b10000 T
b100 S
b1111 R
b11 Q
b0 P
b101011 O
b1 N
b101000 M
b100011 L
b1111 K
b100000 J
b11 I
b10 H
b101 G
b100 F
b1000 E
b101 D
b100010 C
b11 B
b101010 A
b0 @
b11000 ?
b10010 >
b10000 =
b1000 <
b11010 ;
b100100 :
b100000 9
$end
#0
$dumpvars
bx #"
bx ""
b0 !"
bx ~
bx }
bx |
bx {
bx z
bx y
bx x
bx w
xv
bx u
bx t
bx s
xr
xq
bx p
bx o
bx n
z8
z7
bx 6
z5
b0 4
13
bx 2
01
bx 0
bx /
x.
x-
b0 ,
bx +
x*
x)
x(
bx '
x&
x%
x$
x#
bx "
bx !
$end
#5000
b0 s
11
#10000
01
#15000
11
#20000
01
03
#25000
b1 ,
b1 4
b1 !"
0q
0r
b0 0
b0 o
b0 "
b0 ~
b0 '
b0 y
0%
0&
b0 !
b0 ""
b0 +
b0 w
0#
0.
0(
b0 /
b0 p
0)
0*
0-
0v
0$
11
#30000
b10000000000001111 n
b1111 u
b1111 t
b0 }
b0 z
b1 |
b0 {
b1000 x
01
b100000000000010000000000001111 2
b100000000000010000000000001111 6
b100000000000010000000000001111 #"
#35000
b10 ,
b10 4
b10 !"
1&
1*
11
#40000
01
#45000
b1111 ,
b1111 4
b1111 !"
11
#50000
01
#55000
b1 ,
b1 4
b1 !"
1#
b10 /
b10 p
1.
11
#60000
01
#65000
b10 ,
b10 4
b10 !"
1&
0#
0.
b0 /
b0 p
1*
11
#70000
01
#75000
b1000100000000000011001 n
b11001 u
b11001 t
b10 |
b1 {
b1111 ,
b1111 4
b1111 !"
b100000001000100000000000011001 2
b100000001000100000000000011001 6
b100000001000100000000000011001 #"
11
#80000
01
#85000
b1 ,
b1 4
b1 !"
1#
b10 /
b10 p
1.
11
#90000
01
#95000
b10 ,
b10 4
b10 !"
1&
0#
0.
b0 /
b0 p
1*
11
#100000
01
#105000
b1111 ,
b1111 4
b1111 !"
11
#110000
01
#115000
b1 ,
b1 4
b1 !"
1#
b10 /
b10 p
1.
11
#120000
01
#125000
b10000111111111111110110 n
b1111111111110110 u
b110110 t
b11111 }
b11111 z
b11 |
b10 {
b10 ,
b10 4
b10 !"
1&
0#
0.
b0 /
b0 p
1*
b100000010000111111111111110110 2
b100000010000111111111111110110 6
b100000010000111111111111110110 #"
11
#130000
01
#135000
b1111 ,
b1111 4
b1111 !"
11
#140000
01
#145000
b1 ,
b1 4
b1 !"
1#
b10 /
b10 p
1.
11
#150000
01
#155000
b10 ,
b10 4
b10 !"
1&
0#
0.
b0 /
b0 p
1*
11
#160000
01
#165000
b1111 ,
b1111 4
b1111 !"
11
#170000
01
#175000
b10000000000000101 n
b101 u
b101 t
b0 }
b0 z
b1 |
b0 {
b1 ,
b1 4
b1 !"
1#
b10 /
b10 p
1.
b100000000000010000000000000101 2
b100000000000010000000000000101 6
b100000000000010000000000000101 #"
11
#180000
01
#185000
b10 ,
b10 4
b10 !"
1&
0#
0.
b0 /
b0 p
1*
11
#190000
01
#195000
b1111 ,
b1111 4
b1111 !"
11
#200000
01
#205000
b1 ,
b1 4
b1 !"
1#
b10 /
b10 p
1.
11
#210000
01
#215000
b10 ,
b10 4
b10 !"
1&
0#
0.
b0 /
b0 p
1*
11
#220000
01
#225000
b100000000000000101 n
b10 |
b1111 ,
b1111 4
b1111 !"
b100000000000100000000000000101 2
b100000000000100000000000000101 6
b100000000000100000000000000101 #"
11
#230000
01
#235000
b1 ,
b1 4
b1 !"
1#
b10 /
b10 p
1.
11
#240000
01
#245000
b10 ,
b10 4
b10 !"
1&
0#
0.
b0 /
b0 p
1*
11
#250000
01
#255000
b1111 ,
b1111 4
b1111 !"
11
#260000
01
#265000
b1 ,
b1 4
b1 !"
1#
b10 /
b10 p
1.
11
#270000
01
#275000
b1000100000000000000011 n
b11 u
b11 t
b1 {
b100 x
b10 ,
b10 4
b10 !"
1&
0#
0.
b0 /
b0 p
1*
b10000001000100000000000000011 2
b10000001000100000000000000011 6
b10000001000100000000000000011 #"
11
#280000
01
#285000
b10000 ,
b10000 4
b10000 !"
11
#290000
01
#295000
b1 ,
b1 4
b1 !"
b1 '
b1 y
1%
b110 /
b110 p
1-
11
#300000
01
#305000
b10 ,
b10 4
b10 !"
b0 '
b0 y
0%
1&
b0 /
b0 p
1*
0-
11
#310000
01
#315000
b10000 ,
b10000 4
b10000 !"
11
#320000
01
#325000
b110000001111100111 n
b1111100111 u
b100111 t
b1111 }
b11 |
b0 {
b1000 x
b1 ,
b1 4
b1 !"
b1 '
b1 y
1%
b110 /
b110 p
1-
b100000000000110000001111100111 2
b100000000000110000001111100111 6
b100000000000110000001111100111 #"
11
#330000
01
#335000
b10 ,
b10 4
b10 !"
b0 '
b0 y
0%
1&
b0 /
b0 p
1*
0-
11
#340000
01
#345000
b1111 ,
b1111 4
b1111 !"
11
#350000
01
#355000
b1 ,
b1 4
b1 !"
1#
b10 /
b10 p
1.
11
#360000
01
#365000
b10 ,
b10 4
b10 !"
1&
0#
0.
b0 /
b0 p
1*
11
#370000
01
#375000
b10000000000001010 n
b1010 u
b1010 t
b0 }
b1 |
b1111 ,
b1111 4
b1111 !"
b100000000000010000000000001010 2
b100000000000010000000000001010 6
b100000000000010000000000001010 #"
11
#380000
01
#385000
b1 ,
b1 4
b1 !"
1#
b10 /
b10 p
1.
11
#390000
01
#395000
b10 ,
b10 4
b10 !"
1&
0#
0.
b0 /
b0 p
1*
11
#400000
01
#405000
b1111 ,
b1111 4
b1111 !"
11
#410000
01
#415000
b1 ,
b1 4
b1 !"
1#
b10 /
b10 p
1.
11
#420000
01
#425000
b1000100000000000000010 n
b10 u
b10 t
b10 |
b1 {
b101 x
b10 ,
b10 4
b10 !"
1&
0#
0.
b0 /
b0 p
1*
b10100001000100000000000000010 2
b10100001000100000000000000010 6
b10100001000100000000000000010 #"
11
#430000
01
#435000
b10001 ,
b10001 4
b10001 !"
11
#440000
01
#445000
b1 ,
b1 4
b1 !"
b1 '
b1 y
1%
b110 /
b110 p
1-
11
#450000
01
#455000
b10 ,
b10 4
b10 !"
b0 '
b0 y
0%
1&
b0 /
b0 p
1*
0-
11
#460000
01
#465000
b10001 ,
b10001 4
b10001 !"
11
#470000
01
#475000
b1000000001101111000 n
b1101111000 u
b111000 t
b1101 }
b100 |
b0 {
b1000 x
b1 ,
b1 4
b1 !"
b1 '
b1 y
1%
b110 /
b110 p
1-
b100000000001000000001101111000 2
b100000000001000000001101111000 6
b100000000001000000001101111000 #"
11
#480000
01
#485000
b10 ,
b10 4
b10 !"
b0 '
b0 y
0%
1&
b0 /
b0 p
1*
0-
11
#490000
01
#495000
b1111 ,
b1111 4
b1111 !"
11
#500000
01
#505000
b1 ,
b1 4
b1 !"
1#
b10 /
b10 p
1.
11
#510000
01
#515000
b10 ,
b10 4
b10 !"
1&
0#
0.
b0 /
b0 p
1*
11
#520000
01
#525000
b100000000000001010 n
b1010 u
b1010 t
b0 }
b10 |
b1111 ,
b1111 4
b1111 !"
b100000000000100000000000001010 2
b100000000000100000000000001010 6
b100000000000100000000000001010 #"
11
#530000
01
#535000
b1 ,
b1 4
b1 !"
1#
b10 /
b10 p
1.
11
#540000
01
#545000
b10 ,
b10 4
b10 !"
1&
0#
0.
b0 /
b0 p
1*
11
#550000
01
#555000
b1111 ,
b1111 4
b1111 !"
11
#560000
01
