parts_made/control_unit.v
module control_unit(
    input clk,
    input reset,
    input [31:0] instruction,
    input zero_flag,
    input overflow,
    input div_zero,
    
    // Instruction fields
    output reg [5:0] opcode,
    output reg [4:0] rs,
    output reg [4:0] rt,
    output reg [4:0] rd,
    output reg [4:0] shamt,
    output reg [5:0] funct,
    output reg [15:0] immediate,
    output reg [25:0] address,
    
    // ALU controls
    output reg [3:0] alu_control,
    output reg alu_zero,
    output reg alu_overflow,
    
    // Control signals
    output reg reg_dst,
    output reg jump,
    output reg branch,
    output reg mem_read,
    output reg mem_to_reg,
    output reg [3:0] alu_op,
    output reg mem_write,
    output reg alu_src,
    output reg reg_write,
    
    // Load/Store size controls
    output reg [1:0] load_size_control,
    output reg [1:0] store_size_control,
    
    // PC controls
    output reg pc_write,
    output reg pc_write_cond,
    output reg [1:0] pc_source,
    
    // Shift amount control
    output reg [1:0] shift_amt_selector,
    
    // State output
    output [4:0] current_state
);

    // VARIABLES
    reg [4:0] state;     // 5 bits para representar o estado atual
    reg [4:0] counter;   // 5 bits para representar o clk atual em um dado estado
    
    // Instruction field extraction
    always @(*) begin
        opcode = instruction[31:26];
        rs = instruction[25:21];
        rt = instruction[20:16];
        rd = instruction[15:11];
        shamt = instruction[10:6];
        funct = instruction[5:0];
        immediate = instruction[15:0];
        address = instruction[25:0];
    end
    
    // Assign current state to output
    assign current_state = state;

    // STATE PARAMETERS
    parameter ST_RESET          = 5'b00000;
    parameter ST_FETCH          = 5'b00001;
    parameter ST_DECODE         = 5'b00010;
    parameter ST_ADD            = 5'b00011;
    parameter ST_AND            = 5'b00100;
    parameter ST_DIV            = 5'b00101;
    parameter ST_MULT           = 5'b00110;
    parameter ST_JR             = 5'b00111;
    parameter ST_MFHI           = 5'b01000;
    parameter ST_MFLO           = 5'b01001;
    parameter ST_SLL            = 5'b01010;
    parameter ST_SLT            = 5'b01011;
    parameter ST_SRA            = 5'b01100;
    parameter ST_SUB            = 5'b01101;
    parameter ST_XCHG           = 5'b01110;
    parameter ST_ADDI           = 5'b01111;
    parameter ST_BEQ            = 5'b10000;
    parameter ST_BNE            = 5'b10001;
    parameter ST_SLLM           = 5'b10010;
    parameter ST_LB             = 5'b10011;
    parameter ST_LUI            = 5'b10100;
    parameter ST_LW             = 5'b10101;
    parameter ST_SB             = 5'b10110;
    parameter ST_SW             = 5'b10111;
    parameter ST_J              = 5'b11000;
    parameter ST_JAL            = 5'b11001;
    parameter ST_OVERFLOW       = 5'b11010;
    parameter ST_OPCODE404      = 5'b11011;
    parameter ST_DIV0           = 5'b11100;

    // Opcodes (instruction type)
    parameter OP_TYPE_R = 6'b000000;
    parameter OP_ADDI   = 6'b001000;
    parameter OP_BEQ    = 6'b000100;
    parameter OP_BNE    = 6'b000101;
    parameter OP_SLLM   = 6'b000001;
    parameter OP_LB     = 6'b100000;
    parameter OP_LUI    = 6'b001111;
    parameter OP_LW     = 6'b100011;
    parameter OP_SB     = 6'b101000;
    parameter OP_SW     = 6'b101011;
    parameter OP_J      = 6'b000010;
    parameter OP_JAL    = 6'b000011;

    // Function codes for R-type instructions
    parameter FUNCT_ADD  = 6'b100000;
    parameter FUNCT_AND  = 6'b100100;
    parameter FUNCT_DIV  = 6'b011010;
    parameter FUNCT_MULT = 6'b011000;
    parameter FUNCT_JR   = 6'b001000;
    parameter FUNCT_MFHI = 6'b010000;
    parameter FUNCT_MFLO = 6'b010010;
    parameter FUNCT_SLL  = 6'b000000;
    parameter FUNCT_SLT  = 6'b101010;
    parameter FUNCT_SRA  = 6'b000011;
    parameter FUNCT_SUB  = 6'b100010;
    parameter FUNCT_XCHG = 6'b000101;

    // Inicialização
    initial begin
        state = ST_RESET;
    end

    // Main state machine
    always @(posedge clk) begin
        if (reset) begin
            state = ST_RESET;
            counter = 5'b00000;
        end else begin
            case (state)
                ST_RESET: handle_reset_state();
                ST_FETCH: handle_fetch_state();
                ST_DECODE: handle_decode_state();
                ST_OVERFLOW: handle_overflow_state();
                ST_OPCODE404: handle_opcode404_state();
                ST_DIV0: handle_div0_state();
                ST_ADD: handle_add_state();
                ST_AND: handle_and_state();
                ST_DIV: handle_div_state();
                ST_MULT: handle_mult_state();
                ST_JR: handle_jr_state();
                ST_MFHI: handle_mfhi_state();
                ST_MFLO: handle_mflo_state();
                ST_SLL: handle_sll_state();
                ST_SLT: handle_slt_state();
                ST_SRA: handle_sra_state();
                ST_SUB: handle_sub_state();
                ST_XCHG: handle_xchg_state();
                ST_ADDI: handle_addi_state();
                ST_BEQ: handle_beq_state();
                ST_BNE: handle_bne_state();
                ST_SLLM: handle_sllm_state();
                ST_LB: handle_lb_state();
                ST_LUI: handle_lui_state();
                ST_LW: handle_lw_state();
                ST_SB: handle_sb_state();
                ST_SW: handle_sw_state();
                ST_J: handle_j_state();
                ST_JAL: handle_jal_state();
                default: state = ST_OPCODE404;
            endcase
        end
    end

    // TASKS
    task reset_control_signals;
        begin
            // Control signals
            reg_dst = 1'b0;
            jump = 1'b0;
            branch = 1'b0;
            mem_read = 1'b0;
            mem_to_reg = 1'b0;
            alu_op = 4'b0000;
            mem_write = 1'b0;
            alu_src = 1'b0;
            reg_write = 1'b0;
            
            // Load/Store size controls
            load_size_control = 2'b00;
            store_size_control = 2'b00;
            
            // PC controls
            pc_write = 1'b0;
            pc_write_cond = 1'b0;
            pc_source = 2'b00;
            
            // Shift amount control
            shift_amt_selector = 2'b00;
            
            // ALU controls
            alu_control = 4'b0000;
            alu_zero = 1'b0;
            alu_overflow = 1'b0;
        end
    endtask

    // Tasks para cada estado
    task handle_reset_state;
        begin
            reset_control_signals();
            state = ST_FETCH;
            counter = 5'b00000;
        end
    endtask

    task handle_fetch_state;
        begin
            // Reset todos os sinais de controle no FETCH
            reset_control_signals();
            
            // Configurar sinais específicos do FETCH
            mem_read = 1'b1;
            pc_write = 1'b1;
            pc_source = 2'b00; // PC + 4
            
            state = ST_DECODE;
            counter = 5'b00000;
        end
    endtask

    task handle_decode_state;
        begin
            counter = 5'b00000;
            decode_instruction();
        end
    endtask

    task decode_instruction;
        begin
            case (opcode)
                OP_TYPE_R: begin
                    case (funct)
                        FUNCT_ADD:  state = ST_ADD;
                        FUNCT_AND:  state = ST_AND;
                        FUNCT_DIV:  state = ST_DIV;
                        FUNCT_MULT: state = ST_MULT;
                        FUNCT_JR:   state = ST_JR;
                        FUNCT_MFHI: state = ST_MFHI;
                        FUNCT_MFLO: state = ST_MFLO;
                        FUNCT_SLL:  state = ST_SLL;
                        FUNCT_SLT:  state = ST_SLT;
                        FUNCT_SRA:  state = ST_SRA;
                        FUNCT_SUB:  state = ST_SUB;
                        FUNCT_XCHG: state = ST_XCHG;
                        default:    state = ST_OPCODE404;
                    endcase
                end
                OP_ADDI:    state = ST_ADDI;
                OP_BEQ:     state = ST_BEQ;
                OP_BNE:     state = ST_BNE;
                OP_SLLM:    state = ST_SLLM;
                OP_LB:      state = ST_LB;
                OP_LUI:     state = ST_LUI;
                OP_LW:      state = ST_LW;
                OP_SB:      state = ST_SB;
                OP_SW:      state = ST_SW;
                OP_J:       state = ST_J;
                OP_JAL:     state = ST_JAL;
                default:    state = ST_OPCODE404;
            endcase
        end
    endtask

    // R-type instruction tasks
    task handle_add_state;
        begin
            reg_dst = 1'b1;
            alu_op = 4'b0010; // ADD
            alu_control = 4'b0010; // ADD
            reg_write = 1'b1;
            if (overflow) state = ST_OVERFLOW;
            else state = ST_FETCH;
        end
    endtask

    task handle_and_state;
        begin
            reg_dst = 1'b1;
            alu_op = 4'b0001; // AND
            alu_control = 4'b0001; // AND
            reg_write = 1'b1;
            state = ST_FETCH;
        end
    endtask

    task handle_div_state;
        begin
            alu_op = 4'b1001; // DIV
            alu_control = 4'b1001; // DIV
            if (div_zero) state = ST_DIV0;
            else state = ST_FETCH;
        end
    endtask

    task handle_mult_state;
        begin
            alu_op = 4'b1010; // MULT
            alu_control = 4'b1010; // MULT
            state = ST_FETCH;
        end
    endtask

    task handle_jr_state;
        begin
            pc_write = 1'b1;
            pc_source = 2'b10; // Register
            state = ST_FETCH;
        end
    endtask

    task handle_mfhi_state;
        begin
            reg_dst = 1'b1;
            alu_op = 4'b1100; // MFHI
            alu_control = 4'b1100; // MFHI
            reg_write = 1'b1;
            state = ST_FETCH;
        end
    endtask

    task handle_mflo_state;
        begin
            reg_dst = 1'b1;
            alu_op = 4'b1101; // MFLO
            alu_control = 4'b1101; // MFLO
            reg_write = 1'b1;
            state = ST_FETCH;
        end
    endtask

    task handle_sll_state;
        begin
            reg_dst = 1'b1;
            alu_op = 4'b0100; // SLL
            alu_control = 4'b0100; // SLL
            reg_write = 1'b1;
            shift_amt_selector = 2'b11; // Use shamt from instruction
            state = ST_FETCH;
        end
    endtask

    task handle_slt_state;
        begin
            reg_dst = 1'b1;
            alu_op = 4'b0111; // SLT
            alu_control = 4'b0111; // SLT
            reg_write = 1'b1;
            state = ST_FETCH;
        end
    endtask

    task handle_sra_state;
        begin
            reg_dst = 1'b1;
            alu_op = 4'b0101; // SRA
            alu_control = 4'b0101; // SRA
            reg_write = 1'b1;
            shift_amt_selector = 2'b11; // Use shamt from instruction
            state = ST_FETCH;
        end
    endtask

    task handle_sub_state;
        begin
            reg_dst = 1'b1;
            alu_op = 4'b0110; // SUB
            alu_control = 4'b0110; // SUB
            reg_write = 1'b1;
            if (overflow) state = ST_OVERFLOW;
            else state = ST_FETCH;
        end
    endtask

    task handle_xchg_state;
        begin
            reg_dst = 1'b1;
            alu_op = 4'b1011; // XCHG
            alu_control = 4'b1011; // XCHG
            reg_write = 1'b1;
            state = ST_FETCH;
        end
    endtask

    // I-type instruction tasks
    task handle_addi_state;
        begin
            alu_src = 1'b1; // Immediate
            alu_op = 4'b0010; // ADD
            reg_write = 1'b1;
            if (overflow) state = ST_OVERFLOW;
            else state = ST_FETCH;
        end
    endtask

    task handle_beq_state;
        begin
            branch = 1'b1;
            alu_op = 4'b0110; // SUB for comparison
            pc_write_cond = 1'b1;
            pc_source = 2'b01; // Branch target
            state = ST_FETCH;
        end
    endtask

    task handle_bne_state;
        begin
            branch = 1'b1;
            alu_op = 4'b0110; // SUB for comparison
            pc_write_cond = 1'b1;
            pc_source = 2'b01; // Branch target
            state = ST_FETCH;
        end
    endtask

    task handle_sllm_state;
        begin
            alu_src = 1'b1; // Immediate
            alu_op = 4'b0100; // SLL
            reg_write = 1'b1;
            state = ST_FETCH;
        end
    endtask

    task handle_lb_state;
        begin
            alu_src = 1'b1; // Immediate
            alu_op = 4'b0010; // ADD for address calculation
            mem_read = 1'b1;
            mem_to_reg = 1'b1;
            reg_write = 1'b1;
            load_size_control = 2'b00; // Load byte - 1 byte
            state = ST_FETCH;
        end
    endtask

    task handle_lui_state;
        begin
            alu_src = 1'b1; // Immediate
            alu_op = 4'b1000; // LUI
            reg_write = 1'b1;
            state = ST_FETCH;
        end
    endtask

    task handle_lw_state;
        begin
            alu_src = 1'b1; // Immediate
            alu_op = 4'b0010; // ADD for address calculation
            mem_read = 1'b1;
            mem_to_reg = 1'b1;
            reg_write = 1'b1;
            load_size_control = 2'b10; // Load word - 4 bytes
            state = ST_FETCH;
        end
    endtask

    task handle_sb_state;
        begin
            alu_src = 1'b1; // Immediate
            alu_op = 4'b0010; // ADD for address calculation
            mem_write = 1'b1;
            store_size_control = 2'b00; // Store byte - 1 byte
            state = ST_FETCH;
        end
    endtask

    task handle_sw_state;
        begin
            alu_src = 1'b1; // Immediate
            alu_op = 4'b0010; // ADD for address calculation
            mem_write = 1'b1;
            store_size_control = 2'b10; // Store word - 4 bytes
            state = ST_FETCH;
        end
    endtask

    // J-type instruction tasks
    task handle_j_state;
        begin
            jump = 1'b1;
            pc_write = 1'b1;
            pc_source = 2'b11; // Jump target
            state = ST_FETCH;
        end
    endtask

    task handle_jal_state;
        begin
            jump = 1'b1;
            pc_write = 1'b1;
            pc_source = 2'b11; // Jump target
            reg_write = 1'b1; // Write return address to $ra
            state = ST_FETCH;
        end
    endtask

    // Exception handling tasks
    task handle_overflow_state;
        begin
            pc_write = 1'b1;
            pc_source = 2'b11; // Exception handler address
            state = ST_FETCH;
        end
    endtask

    task handle_opcode404_state;
        begin
            pc_write = 1'b1;
            pc_source = 2'b11; // Exception handler address
            state = ST_FETCH;
        end
    endtask

    task handle_div0_state;
        begin
            pc_write = 1'b1;
            pc_source = 2'b11; // Exception handler address
            state = ST_FETCH;
        end
    endtask

endmodule

parts_made/test/R-type/test_r_type.v
// Teste das Instruções R-type
`timescale 1ns/1ps

module test_r_type;
    // Sinais de entrada
    reg clk;
    reg reset;
    reg [31:0] instruction;
    reg zero_flag;
    reg overflow;
    reg div_zero;
    
    // Sinais de saída
    wire [4:0] current_state;
    wire [5:0] opcode;
    wire [4:0] rs, rt, rd;
    wire [4:0] shamt;
    wire [5:0] funct;
    wire [15:0] immediate;
    wire [25:0] address;
    wire [3:0] alu_control;
    wire alu_zero, alu_overflow;
    wire reg_dst, jump, branch, mem_read, mem_to_reg;
    wire [1:0] alu_op;
    wire mem_write, alu_src, reg_write;
    wire pc_write, pc_write_cond;
    wire [1:0] pc_source;
    
    // Instanciação do módulo control_unit
    control_unit uut (
        .clk(clk),
        .reset(reset),
        .instruction(instruction),
        .zero_flag(zero_flag),
        .overflow(overflow),
        .div_zero(div_zero),
        
        // Instruction fields (outputs)
        .opcode(opcode),
        .rs(rs),
        .rt(rt),
        .rd(rd),
        .shamt(shamt),
        .funct(funct),
        .immediate(immediate),
        .address(address),
        
        // ALU controls
        .alu_control(alu_control),
        .alu_zero(alu_zero),
        .alu_overflow(alu_overflow),
        
        // Control signals
        .reg_dst(reg_dst),
        .jump(jump),
        .branch(branch),
        .mem_read(mem_read),
        .mem_to_reg(mem_to_reg),
        .alu_op(alu_op),
        .mem_write(mem_write),
        .alu_src(alu_src),
        .reg_write(reg_write),
        
        // PC controls
        .pc_write(pc_write),
        .pc_write_cond(pc_write_cond),
        .pc_source(pc_source),
        
        // State output
        .current_state(current_state)
    );
    
    // Geração do clock
    initial begin
        clk = 0;
        forever #5 clk = ~clk;
    end
    
    // Task para reset do sistema
    task reset_system;
        begin
            reset = 1;
            instruction = 32'h00000000;
            zero_flag = 0;
            overflow = 0;
            div_zero = 0;
            #20;
            reset = 0;
            #10;
        end
    endtask
    
    // Task para aguardar ciclos
    task wait_cycles;
        input integer cycles;
        begin
            repeat(cycles) @(posedge clk);
        end
    endtask
    
    // Task para executar uma instrução
    task execute_instruction;
        input [31:0] instr;
        begin
            instruction = instr;
            wait_cycles(3); // FETCH -> DECODE -> EXECUTE
        end
    endtask
    
    // Início dos testes
    initial begin
        $dumpfile("test_r_type.vcd");
        $dumpvars(0, test_r_type);
        
        reset_system();
        
        $display("=== TESTE 1: AND ===");
        execute_instruction({6'h08, 5'd0, 5'd1, 16'd12});    // addiu $1, $zero, 12
        execute_instruction({6'h08, 5'd0, 5'd2, 16'd14});    // addiu $2, $zero, 14
        execute_instruction({6'h00, 5'd1, 5'd2, 5'd3, 5'd0, 6'h24}); // and $3, $1, $2
        $display("Teste AND concluído\n");
        
        $display("=== TESTE 2: DIV, MFHI, MFLO ===");
        execute_instruction({6'h08, 5'd0, 5'd1, 16'd21});    // addiu $1, $zero, 21
        execute_instruction({6'h08, 5'd0, 5'd2, 16'd7});     // addiu $2, $zero, 7
        execute_instruction({6'h00, 5'd1, 5'd2, 5'd0, 5'd0, 6'h1a}); // div $1, $2
        execute_instruction({6'h00, 5'd0, 5'd0, 5'd3, 5'd0, 6'h10}); // mfhi $3
        execute_instruction({6'h00, 5'd0, 5'd0, 5'd4, 5'd0, 6'h12}); // mflo $4
        $display("Teste DIV, MFHI, MFLO concluído\n");
        
        $display("=== TESTE 3: MULT, MFHI, MFLO ===");
        execute_instruction({6'h08, 5'd0, 5'd1, 16'd4});     // addiu $1, $zero, 4
        execute_instruction({6'h08, 5'd0, 5'd2, 16'd3});     // addiu $2, $zero, 3
        execute_instruction({6'h00, 5'd1, 5'd2, 5'd0, 5'd0, 6'h18}); // mult $1, $2
        execute_instruction({6'h00, 5'd0, 5'd0, 5'd2, 5'd0, 6'h10}); // mfhi $2
        execute_instruction({6'h00, 5'd0, 5'd0, 5'd1, 5'd0, 6'h12}); // mflo $1
        $display("Teste MULT, MFHI, MFLO concluído\n");
        
        $display("=== TESTE 4: SLL ===");
        execute_instruction({6'h08, 5'd0, 5'd3, 16'd32});    // addiu $3, $zero, 32
        execute_instruction({6'h00, 5'd0, 5'd3, 5'd3, 5'd4, 6'h00}); // sll $3, $3, 4
        $display("Teste SLL concluído\n");
        
        $display("=== TESTE 5: SLT ===");
        execute_instruction({6'h08, 5'd0, 5'd1, 16'd3});     // addiu $1, $zero, 3
        execute_instruction({6'h08, 5'd0, 5'd2, 16'd4});     // addiu $2, $zero, 4
        execute_instruction({6'h00, 5'd1, 5'd2, 5'd3, 5'd0, 6'h2a}); // slt $3, $1, $2
        execute_instruction({6'h00, 5'd2, 5'd2, 5'd3, 5'd0, 6'h2a}); // slt $3, $2, $2
        execute_instruction({6'h08, 5'd0, 5'd3, 16'd1});     // addiu $3, $zero, 1
        execute_instruction({6'h00, 5'd2, 5'd1, 5'd3, 5'd0, 6'h2a}); // slt $3, $2, $1
        $display("Teste SLT concluído\n");
        
        $display("=== TESTE 6: SRA ===");
        execute_instruction({6'h08, 5'd0, 5'd1, 16'hfffa});  // addiu $1, $zero, -6
        execute_instruction({6'h00, 5'd0, 5'd1, 5'd1, 5'd1, 6'h03}); // sra $1, $1, 1
        $display("Teste SRA concluído\n");
        
        $display("=== TESTE 7: SUB ===");
        execute_instruction({6'h08, 5'd0, 5'd1, 16'd15});    // addiu $1, $zero, 15
        execute_instruction({6'h08, 5'd0, 5'd2, 16'd10});    // addiu $2, $zero, 10
        execute_instruction({6'h00, 5'd1, 5'd2, 5'd3, 5'd0, 6'h22}); // sub $3, $1, $2
        $display("Teste SUB concluído\n");
        
        $display("=== TESTE 8: XCHG ===");
        execute_instruction({6'h08, 5'd0, 5'd1, 16'd2});     // addiu $1, $zero, 2
        execute_instruction({6'h08, 5'd0, 5'd2, 16'd3});     // addiu $2, $zero, 3
        execute_instruction({6'h00, 5'd1, 5'd2, 5'd0, 5'd0, 6'h05}); // xchg $1, $2
        $display("Teste XCHG concluído\n");
        
        $display("=== TESTE 9: ADD ===");
        execute_instruction({6'h08, 5'd0, 5'd1, 16'd3});     // addiu $1, $zero, 3
        execute_instruction({6'h08, 5'd0, 5'd2, 16'd4});     // addiu $2, $zero, 4
        execute_instruction({6'h00, 5'd1, 5'd2, 5'd3, 5'd0, 6'h20}); // add $3, $1, $2
        $display("Teste ADD concluído\n");
        
        $display("=== TESTE 10: JR ===");
        execute_instruction({6'h08, 5'd0, 5'd31, 16'd20});   // addiu $31, $zero, 20
        execute_instruction({6'h00, 5'd31, 5'd0, 5'd0, 5'd0, 6'h08}); // jr $31
        execute_instruction({6'h08, 5'd0, 5'd0, 16'd20});    // addiu $0, $zero, 20
        $display("Teste JR concluído\n");
        
        $display("=== TODOS OS TESTES R-TYPE CONCLUÍDOS ===");
        $finish;
    end
    
endmodule

parts_made/test/R-type/test_r_type.vcd
$date
	Mon Jul 14 00:02:12 2025
$end
$version
	Icarus Verilog
$end
$timescale
	1ps
$end
$scope module test_r_type $end
$var wire 5 ! shamt [4:0] $end
$var wire 5 " rt [4:0] $end
$var wire 5 # rs [4:0] $end
$var wire 1 $ reg_write $end
$var wire 1 % reg_dst $end
$var wire 5 & rd [4:0] $end
$var wire 1 ' pc_write_cond $end
$var wire 1 ( pc_write $end
$var wire 2 ) pc_source [1:0] $end
$var wire 6 * opcode [5:0] $end
$var wire 1 + mem_write $end
$var wire 1 , mem_to_reg $end
$var wire 1 - mem_read $end
$var wire 1 . jump $end
$var wire 16 / immediate [15:0] $end
$var wire 6 0 funct [5:0] $end
$var wire 5 1 current_state [4:0] $end
$var wire 1 2 branch $end
$var wire 1 3 alu_zero $end
$var wire 1 4 alu_src $end
$var wire 1 5 alu_overflow $end
$var wire 2 6 alu_op [1:0] $end
$var wire 4 7 alu_control [3:0] $end
$var wire 26 8 address [25:0] $end
$var reg 1 9 clk $end
$var reg 1 : div_zero $end
$var reg 32 ; instruction [31:0] $end
$var reg 1 < overflow $end
$var reg 1 = reset $end
$var reg 1 > zero_flag $end
$scope module uut $end
$var wire 1 9 clk $end
$var wire 5 ? current_state [4:0] $end
$var wire 1 : div_zero $end
$var wire 32 @ instruction [31:0] $end
$var wire 1 < overflow $end
$var wire 1 = reset $end
$var wire 1 > zero_flag $end
$var parameter 6 A FUNCT_ADD $end
$var parameter 6 B FUNCT_AND $end
$var parameter 6 C FUNCT_DIV $end
$var parameter 6 D FUNCT_JR $end
$var parameter 6 E FUNCT_MFHI $end
$var parameter 6 F FUNCT_MFLO $end
$var parameter 6 G FUNCT_MULT $end
$var parameter 6 H FUNCT_SLL $end
$var parameter 6 I FUNCT_SLT $end
$var parameter 6 J FUNCT_SRA $end
$var parameter 6 K FUNCT_SUB $end
$var parameter 6 L FUNCT_XCHG $end
$var parameter 6 M OP_ADDI $end
$var parameter 6 N OP_BEQ $end
$var parameter 6 O OP_BNE $end
$var parameter 6 P OP_J $end
$var parameter 6 Q OP_JAL $end
$var parameter 6 R OP_LB $end
$var parameter 6 S OP_LUI $end
$var parameter 6 T OP_LW $end
$var parameter 6 U OP_SB $end
$var parameter 6 V OP_SLLM $end
$var parameter 6 W OP_SW $end
$var parameter 6 X OP_TYPE_R $end
$var parameter 5 Y ST_ADD $end
$var parameter 5 Z ST_ADDI $end
$var parameter 5 [ ST_AND $end
$var parameter 5 \ ST_BEQ $end
$var parameter 5 ] ST_BNE $end
$var parameter 5 ^ ST_DECODE $end
$var parameter 5 _ ST_DIV $end
$var parameter 5 ` ST_DIV0 $end
$var parameter 5 a ST_FETCH $end
$var parameter 5 b ST_J $end
$var parameter 5 c ST_JAL $end
$var parameter 5 d ST_JR $end
$var parameter 5 e ST_LB $end
$var parameter 5 f ST_LUI $end
$var parameter 5 g ST_LW $end
$var parameter 5 h ST_MFHI $end
$var parameter 5 i ST_MFLO $end
$var parameter 5 j ST_MULT $end
$var parameter 5 k ST_OPCODE404 $end
$var parameter 5 l ST_OVERFLOW $end
$var parameter 5 m ST_RESET $end
$var parameter 5 n ST_SB $end
$var parameter 5 o ST_SLL $end
$var parameter 5 p ST_SLLM $end
$var parameter 5 q ST_SLT $end
$var parameter 5 r ST_SRA $end
$var parameter 5 s ST_SUB $end
$var parameter 5 t ST_SW $end
$var parameter 5 u ST_XCHG $end
$var reg 26 v address [25:0] $end
$var reg 4 w alu_control [3:0] $end
$var reg 4 x alu_op [3:0] $end
$var reg 1 5 alu_overflow $end
$var reg 1 4 alu_src $end
$var reg 1 3 alu_zero $end
$var reg 1 2 branch $end
$var reg 5 y counter [4:0] $end
$var reg 6 z funct [5:0] $end
$var reg 16 { immediate [15:0] $end
$var reg 1 . jump $end
$var reg 2 | load_size_control [1:0] $end
$var reg 1 - mem_read $end
$var reg 1 , mem_to_reg $end
$var reg 1 + mem_write $end
$var reg 6 } opcode [5:0] $end
$var reg 2 ~ pc_source [1:0] $end
$var reg 1 ( pc_write $end
$var reg 1 ' pc_write_cond $end
$var reg 5 !" rd [4:0] $end
$var reg 1 % reg_dst $end
$var reg 1 $ reg_write $end
$var reg 5 "" rs [4:0] $end
$var reg 5 #" rt [4:0] $end
$var reg 5 $" shamt [4:0] $end
$var reg 2 %" shift_amt_selector [1:0] $end
$var reg 5 &" state [4:0] $end
$var reg 2 '" store_size_control [1:0] $end
$scope task decode_instruction $end
$upscope $end
$scope task handle_add_state $end
$upscope $end
$scope task handle_addi_state $end
$upscope $end
$scope task handle_and_state $end
$upscope $end
$scope task handle_beq_state $end
$upscope $end
$scope task handle_bne_state $end
$upscope $end
$scope task handle_decode_state $end
$upscope $end
$scope task handle_div0_state $end
$upscope $end
$scope task handle_div_state $end
$upscope $end
$scope task handle_fetch_state $end
$upscope $end
$scope task handle_j_state $end
$upscope $end
$scope task handle_jal_state $end
$upscope $end
$scope task handle_jr_state $end
$upscope $end
$scope task handle_lb_state $end
$upscope $end
$scope task handle_lui_state $end
$upscope $end
$scope task handle_lw_state $end
$upscope $end
$scope task handle_mfhi_state $end
$upscope $end
$scope task handle_mflo_state $end
$upscope $end
$scope task handle_mult_state $end
$upscope $end
$scope task handle_opcode404_state $end
$upscope $end
$scope task handle_overflow_state $end
$upscope $end
$scope task handle_reset_state $end
$upscope $end
$scope task handle_sb_state $end
$upscope $end
$scope task handle_sll_state $end
$upscope $end
$scope task handle_sllm_state $end
$upscope $end
$scope task handle_slt_state $end
$upscope $end
$scope task handle_sra_state $end
$upscope $end
$scope task handle_sub_state $end
$upscope $end
$scope task handle_sw_state $end
$upscope $end
$scope task handle_xchg_state $end
$upscope $end
$scope task reset_control_signals $end
$upscope $end
$upscope $end
$scope task execute_instruction $end
$var reg 32 (" instr [31:0] $end
$upscope $end
$scope task reset_system $end
$upscope $end
$scope task wait_cycles $end
$var integer 32 )" cycles [31:0] $end
$upscope $end
$upscope $end
$enddefinitions $end
$comment Show the parameter values. $end
$dumpall
b1110 u
b10111 t
b1101 s
b1100 r
b1011 q
b10010 p
b1010 o
b10110 n
b0 m
b11010 l
b11011 k
b110 j
b1001 i
b1000 h
b10101 g
b10100 f
b10011 e
b111 d
b11001 c
b11000 b
b1 a
b11100 `
b101 _
b10 ^
b10001 ]
b10000 \
b100 [
b1111 Z
b11 Y
b0 X
b101011 W
b1 V
b101000 U
b100011 T
b1111 S
b100000 R
b11 Q
b10 P
b101 O
b100 N
b1000 M
b101 L
b100010 K
b11 J
b101010 I
b0 H
b11000 G
b10010 F
b10000 E
b1000 D
b11010 C
b100100 B
b100000 A
$end
#0
$dumpvars
bx )"
bx ("
bx '"
b0 &"
bx %"
b0 $"
b0 #"
b0 ""
b0 !"
bx ~
b0 }
bx |
b0 {
b0 z
bx y
bx x
bx w
b0 v
b0 @
b0 ?
0>
1=
0<
b0 ;
0:
09
b0 8
bx 7
bx 6
x5
x4
x3
x2
b0 1
b0 0
b0 /
x.
x-
x,
x+
b0 *
bx )
x(
x'
b0 &
x%
x$
b0 #
b0 "
b0 !
$end
#5000
b0 y
19
#10000
09
#15000
19
#20000
09
0=
#25000
b0 6
b1 1
b1 ?
b1 &"
05
03
b0 7
b0 w
b0 %"
b0 )
b0 ~
0'
0(
b0 '"
b0 |
0$
04
0+
b0 x
0,
0-
02
0.
0%
19
#30000
b10000000000001100 8
b10000000000001100 v
b1100 /
b1100 {
b1100 0
b1100 z
b1 "
b1 #"
b1000 *
b1000 }
09
b11 )"
b100000000000010000000000001100 ;
b100000000000010000000000001100 @
b100000000000010000000000001100 ("
#35000
b10 1
b10 ?
b10 &"
1(
1-
19
#40000
09
#45000
b1111 1
b1111 ?
b1111 &"
19
#50000
09
#55000
b10 6
b100000000000001110 8
b100000000000001110 v
b1110 /
b1110 {
b1110 0
b1110 z
b10 "
b10 #"
b1 1
b1 ?
b1 &"
1$
b10 x
14
b100000000000100000000000001110 ;
b100000000000100000000000001110 @
b100000000000100000000000001110 ("
19
#60000
09
#65000
b0 6
b10 1
b10 ?
b10 &"
1(
0$
04
b0 x
1-
19
#70000
09
#75000
b1111 1
b1111 ?
b1111 &"
19
#80000
09
#85000
b10 6
b1000100001100000100100 8
b1000100001100000100100 v
b1100000100100 /
b1100000100100 {
b100100 0
b100100 z
b11 &
b11 !"
b1 #
b1 ""
b0 *
b0 }
b1 1
b1 ?
b1 &"
1$
b10 x
14
b1000100001100000100100 ;
b1000100001100000100100 @
b1000100001100000100100 ("
19
#90000
09
#95000
b0 6
b10 1
b10 ?
b10 &"
1(
0$
04
b0 x
1-
19
#100000
09
#105000
b100 1
b100 ?
b100 &"
19
#110000
09
#115000
b1 6
b10000000000010101 8
b10000000000010101 v
b10101 /
b10101 {
b10101 0
b10101 z
b0 &
b0 !"
b1 "
b1 #"
b0 #
b0 ""
b1000 *
b1000 }
b1 1
b1 ?
b1 &"
1$
b1 7
b1 w
b1 x
1%
b100000000000010000000000010101 ;
b100000000000010000000000010101 @
b100000000000010000000000010101 ("
19
#120000
09
#125000
b0 6
b10 1
b10 ?
b10 &"
b0 7
b0 w
1(
0$
b0 x
1-
0%
19
#130000
09
#135000
b1111 1
b1111 ?
b1111 &"
19
#140000
09
#145000
b10 6
b100000000000000111 8
b100000000000000111 v
b111 /
b111 {
b111 0
b111 z
b10 "
b10 #"
b1 1
b1 ?
b1 &"
1$
b10 x
14
b100000000000100000000000000111 ;
b100000000000100000000000000111 @
b100000000000100000000000000111 ("
19
#150000
09
#155000
b0 6
b10 1
b10 ?
b10 &"
1(
0$
04
b0 x
1-
19
#160000
09
#165000
b1111 1
b1111 ?
b1111 &"
19
#170000
09
#175000
b10 6
b1000100000000000011010 8
b1000100000000000011010 v
b11010 /
b11010 {
b11010 0
b11010 z
b1 #
b1 ""
b0 *
b0 }
b1 1
b1 ?
b1 &"
1$
b10 x
14
b1000100000000000011010 ;
b1000100000000000011010 @
b1000100000000000011010 ("
19
#180000
09
#185000
b0 6
b10 1
b10 ?
b10 &"
1(
0$
04
b0 x
1-
19
#190000
09
#195000
b101 1
b101 ?
b101 &"
19
#200000
09
#205000
b1 6
b1100000010000 8
b1100000010000 v
b1100000010000 /
b1100000010000 {
b10000 0
b10000 z
b11 &
b11 !"
b0 "
b0 #"
b0 #
b0 ""
b1 1
b1 ?
b1 &"
b1001 7
b1001 w
b1001 x
b1100000010000 ;
b1100000010000 @
b1100000010000 ("
19
#210000
09
#215000
b0 6
b10 1
b10 ?
b10 &"
b0 7
b0 w
1(
b0 x
1-
19
#220000
09
#225000
b1000 1
b1000 ?
b1000 &"
19
#230000
09
