parts_made/control_unit.v
module control_unit(
    input clk,
    input reset,
    input [31:0] instruction,
    input zero_flag,
    input overflow,
    input div_zero,
    
    // Instruction fields
    output reg [5:0] opcode,
    output reg [4:0] rs,
    output reg [4:0] rt,
    output reg [4:0] rd,
    output reg [4:0] shamt,
    output reg [5:0] funct,
    output reg [15:0] immediate,
    output reg [25:0] address,
    
    // ALU controls
    output reg [3:0] alu_control,
    output reg alu_zero,
    output reg alu_overflow,
    
    // Control signals
    output reg reg_dst,
    output reg jump,
    output reg branch,
    output reg mem_read,
    output reg mem_to_reg,
    output reg [3:0] alu_op,
    output reg mem_write,
    output reg alu_src,
    output reg reg_write,
    
    // Load/Store size controls
    output reg [1:0] load_size_control,
    output reg [1:0] store_size_control,
    
    // PC controls
    output reg pc_write,
    output reg pc_write_cond,
    output reg [1:0] pc_source,
    
    // Shift amount control
    output reg [1:0] shift_amt_selector,
    
    // State output
    output [4:0] current_state
);

    // VARIABLES
    reg [4:0] state;     // 5 bits para representar o estado atual
    reg [4:0] counter;   // 5 bits para representar o clk atual em um dado estado
    
    // Instruction field extraction
    always @(*) begin
        opcode = instruction[31:26];
        rs = instruction[25:21];
        rt = instruction[20:16];
        rd = instruction[15:11];
        shamt = instruction[10:6];
        funct = instruction[5:0];
        immediate = instruction[15:0];
        address = instruction[25:0];
    end
    
    // Assign current state to output
    assign current_state = state;

    // STATE PARAMETERS
    parameter ST_RESET          = 5'b00000;
    parameter ST_FETCH          = 5'b00001;
    parameter ST_DECODE         = 5'b00010;
    parameter ST_ADD            = 5'b00011;
    parameter ST_AND            = 5'b00100;
    parameter ST_DIV            = 5'b00101;
    parameter ST_MULT           = 5'b00110;
    parameter ST_JR             = 5'b00111;
    parameter ST_MFHI           = 5'b01000;
    parameter ST_MFLO           = 5'b01001;
    parameter ST_SLL            = 5'b01010;
    parameter ST_SLT            = 5'b01011;
    parameter ST_SRA            = 5'b01100;
    parameter ST_SUB            = 5'b01101;
    parameter ST_XCHG           = 5'b01110;
    parameter ST_ADDI           = 5'b01111;
    parameter ST_BEQ            = 5'b10000;
    parameter ST_BNE            = 5'b10001;
    parameter ST_SLLM           = 5'b10010;
    parameter ST_LB             = 5'b10011;
    parameter ST_LUI            = 5'b10100;
    parameter ST_LW             = 5'b10101;
    parameter ST_SB             = 5'b10110;
    parameter ST_SW             = 5'b10111;
    parameter ST_J              = 5'b11000;
    parameter ST_JAL            = 5'b11001;
    parameter ST_OVERFLOW       = 5'b11010;
    parameter ST_OPCODE404      = 5'b11011;
    parameter ST_DIV0           = 5'b11100;

    // Opcodes (instruction type)
    parameter OP_TYPE_R = 6'b000000;
    parameter OP_ADDI   = 6'b001000;
    parameter OP_BEQ    = 6'b000100;
    parameter OP_BNE    = 6'b000101;
    parameter OP_SLLM   = 6'b000001;
    parameter OP_LB     = 6'b100000;
    parameter OP_LUI    = 6'b001111;
    parameter OP_LW     = 6'b100011;
    parameter OP_SB     = 6'b101000;
    parameter OP_SW     = 6'b101011;
    parameter OP_J      = 6'b000010;
    parameter OP_JAL    = 6'b000011;

    // Function codes for R-type instructions
    parameter FUNCT_ADD  = 6'b100000;
    parameter FUNCT_AND  = 6'b100100;
    parameter FUNCT_DIV  = 6'b011010;
    parameter FUNCT_MULT = 6'b011000;
    parameter FUNCT_JR   = 6'b001000;
    parameter FUNCT_MFHI = 6'b010000;
    parameter FUNCT_MFLO = 6'b010010;
    parameter FUNCT_SLL  = 6'b000000;
    parameter FUNCT_SLT  = 6'b101010;
    parameter FUNCT_SRA  = 6'b000011;
    parameter FUNCT_SUB  = 6'b100010;
    parameter FUNCT_XCHG = 6'b000101;

    // Inicialização
    initial begin
        state = ST_RESET;
    end

    // Main state machine
    always @(posedge clk) begin
        if (reset) begin
            state = ST_RESET;
            counter = 5'b00000;
        end else begin
            case (state)
                ST_RESET: handle_reset_state();
                ST_FETCH: handle_fetch_state();
                ST_DECODE: handle_decode_state();
                ST_OVERFLOW: handle_overflow_state();
                ST_OPCODE404: handle_opcode404_state();
                ST_DIV0: handle_div0_state();
                ST_ADD: handle_add_state();
                ST_AND: handle_and_state();
                ST_DIV: handle_div_state();
                ST_MULT: handle_mult_state();
                ST_JR: handle_jr_state();
                ST_MFHI: handle_mfhi_state();
                ST_MFLO: handle_mflo_state();
                ST_SLL: handle_sll_state();
                ST_SLT: handle_slt_state();
                ST_SRA: handle_sra_state();
                ST_SUB: handle_sub_state();
                ST_XCHG: handle_xchg_state();
                ST_ADDI: handle_addi_state();
                ST_BEQ: handle_beq_state();
                ST_BNE: handle_bne_state();
                ST_SLLM: handle_sllm_state();
                ST_LB: handle_lb_state();
                ST_LUI: handle_lui_state();
                ST_LW: handle_lw_state();
                ST_SB: handle_sb_state();
                ST_SW: handle_sw_state();
                ST_J: handle_j_state();
                ST_JAL: handle_jal_state();
                default: state = ST_OPCODE404;
            endcase
        end
    end

    // TASKS
    task reset_control_signals;
        begin
            // Control signals
            reg_dst = 1'b0;
            jump = 1'b0;
            branch = 1'b0;
            mem_read = 1'b0;
            mem_to_reg = 1'b0;
            alu_op = 4'b0000;
            mem_write = 1'b0;
            alu_src = 1'b0;
            reg_write = 1'b0;
            
            // Load/Store size controls
            load_size_control = 2'b00;
            store_size_control = 2'b00;
            
            // PC controls
            pc_write = 1'b0;
            pc_write_cond = 1'b0;
            pc_source = 2'b00;
            
            // Shift amount control
            shift_amt_selector = 2'b00;
            
            // ALU controls
            alu_control = 4'b0000;
            alu_zero = 1'b0;
            alu_overflow = 1'b0;
        end
    endtask

    // Tasks para cada estado
    task handle_reset_state;
        begin
            reset_control_signals();
            state = ST_FETCH;
            counter = 5'b00000;
        end
    endtask

    task handle_fetch_state;
        begin
            // Reset todos os sinais de controle no FETCH
            reset_control_signals();
            
            // Configurar sinais específicos do FETCH
            mem_read = 1'b1;
            pc_write = 1'b1;
            pc_source = 2'b00; // PC + 4
            
            state = ST_DECODE;
            counter = 5'b00000;
        end
    endtask

    task handle_decode_state;
        begin
            counter = 5'b00000;
            decode_instruction();
        end
    endtask

    task decode_instruction;
        begin
            case (opcode)
                OP_TYPE_R: begin
                    case (funct)
                        FUNCT_ADD:  state = ST_ADD;
                        FUNCT_AND:  state = ST_AND;
                        FUNCT_DIV:  state = ST_DIV;
                        FUNCT_MULT: state = ST_MULT;
                        FUNCT_JR:   state = ST_JR;
                        FUNCT_MFHI: state = ST_MFHI;
                        FUNCT_MFLO: state = ST_MFLO;
                        FUNCT_SLL:  state = ST_SLL;
                        FUNCT_SLT:  state = ST_SLT;
                        FUNCT_SRA:  state = ST_SRA;
                        FUNCT_SUB:  state = ST_SUB;
                        FUNCT_XCHG: state = ST_XCHG;
                        default:    state = ST_OPCODE404;
                    endcase
                end
                OP_ADDI:    state = ST_ADDI;
                OP_BEQ:     state = ST_BEQ;
                OP_BNE:     state = ST_BNE;
                OP_SLLM:    state = ST_SLLM;
                OP_LB:      state = ST_LB;
                OP_LUI:     state = ST_LUI;
                OP_LW:      state = ST_LW;
                OP_SB:      state = ST_SB;
                OP_SW:      state = ST_SW;
                OP_J:       state = ST_J;
                OP_JAL:     state = ST_JAL;
                default:    state = ST_OPCODE404;
            endcase
        end
    endtask

    // R-type instruction tasks
    task handle_add_state;
        begin
            reg_dst = 1'b1;
            alu_op = 4'b0010; // ADD
            alu_control = 4'b0010; // ADD
            reg_write = 1'b1;
            if (overflow) state = ST_OVERFLOW;
            else state = ST_FETCH;
        end
    endtask

    task handle_and_state;
        begin
            reg_dst = 1'b1;
            alu_op = 4'b0001; // AND
            alu_control = 4'b0001; // AND
            reg_write = 1'b1;
            state = ST_FETCH;
        end
    endtask

    task handle_div_state;
        begin
            alu_op = 4'b1001; // DIV
            alu_control = 4'b1001; // DIV
            if (div_zero) state = ST_DIV0;
            else state = ST_FETCH;
        end
    endtask

    task handle_mult_state;
        begin
            alu_op = 4'b1010; // MULT
            alu_control = 4'b1010; // MULT
            state = ST_FETCH;
        end
    endtask

    task handle_jr_state;
        begin
            pc_write = 1'b1;
            pc_source = 2'b10; // Register
            state = ST_FETCH;
        end
    endtask

    task handle_mfhi_state;
        begin
            reg_dst = 1'b1;
            alu_op = 4'b1100; // MFHI
            alu_control = 4'b1100; // MFHI
            reg_write = 1'b1;
            state = ST_FETCH;
        end
    endtask

    task handle_mflo_state;
        begin
            reg_dst = 1'b1;
            alu_op = 4'b1101; // MFLO
            alu_control = 4'b1101; // MFLO
            reg_write = 1'b1;
            state = ST_FETCH;
        end
    endtask

    task handle_sll_state;
        begin
            reg_dst = 1'b1;
            alu_op = 4'b0100; // SLL
            alu_control = 4'b0100; // SLL
            reg_write = 1'b1;
            shift_amt_selector = 2'b11; // Use shamt from instruction
            state = ST_FETCH;
        end
    endtask

    task handle_slt_state;
        begin
            reg_dst = 1'b1;
            alu_op = 4'b0111; // SLT
            alu_control = 4'b0111; // SLT
            reg_write = 1'b1;
            state = ST_FETCH;
        end
    endtask

    task handle_sra_state;
        begin
            reg_dst = 1'b1;
            alu_op = 4'b0101; // SRA
            alu_control = 4'b0101; // SRA
            reg_write = 1'b1;
            shift_amt_selector = 2'b11; // Use shamt from instruction
            state = ST_FETCH;
        end
    endtask

    task handle_sub_state;
        begin
            reg_dst = 1'b1;
            alu_op = 4'b0110; // SUB
            alu_control = 4'b0110; // SUB
            reg_write = 1'b1;
            if (overflow) state = ST_OVERFLOW;
            else state = ST_FETCH;
        end
    endtask

    task handle_xchg_state;
        begin
            reg_dst = 1'b1;
            alu_op = 4'b1011; // XCHG
            alu_control = 4'b1011; // XCHG
            reg_write = 1'b1;
            state = ST_FETCH;
        end
    endtask

    // I-type instruction tasks
    task handle_addi_state;
        begin
            alu_src = 1'b1; // Immediate
            alu_op = 4'b0010; // ADD
            reg_write = 1'b1;
            if (overflow) state = ST_OVERFLOW;
            else state = ST_FETCH;
        end
    endtask

    task handle_beq_state;
        begin
            branch = 1'b1;
            alu_op = 4'b0110; // SUB for comparison
            pc_write_cond = 1'b1;
            pc_source = 2'b01; // Branch target
            state = ST_FETCH;
        end
    endtask

    task handle_bne_state;
        begin
            branch = 1'b1;
            alu_op = 4'b0110; // SUB for comparison
            pc_write_cond = 1'b1;
            pc_source = 2'b01; // Branch target
            state = ST_FETCH;
        end
    endtask

    task handle_sllm_state;
        begin
            alu_src = 1'b1; // Immediate
            alu_op = 4'b0100; // SLL
            reg_write = 1'b1;
            state = ST_FETCH;
        end
    endtask

    task handle_lb_state;
        begin
            alu_src = 1'b1; // Immediate
            alu_op = 4'b0010; // ADD for address calculation
            mem_read = 1'b1;
            mem_to_reg = 1'b1;
            reg_write = 1'b1;
            load_size_control = 2'b00; // Load byte - 1 byte
            state = ST_FETCH;
        end
    endtask

    task handle_lui_state;
        begin
            alu_src = 1'b1; // Immediate
            alu_op = 4'b1000; // LUI
            reg_write = 1'b1;
            state = ST_FETCH;
        end
    endtask

    task handle_lw_state;
        begin
            alu_src = 1'b1; // Immediate
            alu_op = 4'b0010; // ADD for address calculation
            mem_read = 1'b1;
            mem_to_reg = 1'b1;
            reg_write = 1'b1;
            load_size_control = 2'b10; // Load word - 4 bytes
            state = ST_FETCH;
        end
    endtask

    task handle_sb_state;
        begin
            alu_src = 1'b1; // Immediate
            alu_op = 4'b0010; // ADD for address calculation
            mem_write = 1'b1;
            store_size_control = 2'b00; // Store byte - 1 byte
            state = ST_FETCH;
        end
    endtask

    task handle_sw_state;
        begin
            alu_src = 1'b1; // Immediate
            alu_op = 4'b0010; // ADD for address calculation
            mem_write = 1'b1;
            store_size_control = 2'b10; // Store word - 4 bytes
            state = ST_FETCH;
        end
    endtask

    // J-type instruction tasks
    task handle_j_state;
        begin
            jump = 1'b1;
            pc_write = 1'b1;
            pc_source = 2'b11; // Jump target
            state = ST_FETCH;
        end
    endtask

    task handle_jal_state;
        begin
            jump = 1'b1;
            pc_write = 1'b1;
            pc_source = 2'b11; // Jump target
            reg_write = 1'b1; // Write return address to $ra
            state = ST_FETCH;
        end
    endtask

    // Exception handling tasks
    task handle_overflow_state;
        begin
            pc_write = 1'b1;
            pc_source = 2'b11; // Exception handler address
            state = ST_FETCH;
        end
    endtask

    task handle_opcode404_state;
        begin
            pc_write = 1'b1;
            pc_source = 2'b11; // Exception handler address
            state = ST_FETCH;
        end
    endtask

    task handle_div0_state;
        begin
            pc_write = 1'b1;
            pc_source = 2'b11; // Exception handler address
            state = ST_FETCH;
        end
    endtask

endmodule

parts_made/test/J-type/test_j_type.v
`timescale 1ns/1ps

module test_j_type;
    // Sinais
    reg clk;
    reg reset;
    reg [31:0] instruction;
    
    // Saídas da control_unit
    wire [3:0] alu_control;
    wire [3:0] alu_op;
    wire reg_write;
    wire mem_read;
    wire mem_write;
    wire pc_write;
    wire branch;
    wire jump;
    wire alu_src;
    wire reg_dst;
    wire mem_to_reg;
    wire [1:0] load_size_control;
    wire [1:0] store_size_control;
    wire [1:0] shift_amt_selector;
    wire [1:0] pc_source;
    wire pc_write_cond;
    wire [4:0] current_state;
    
    // Instanciação da control_unit
    control_unit uut (
        .clk(clk),
        .reset(reset),
        .instruction(instruction),
        .alu_control(alu_control),
        .alu_op(alu_op),
        .reg_write(reg_write),
        .mem_read(mem_read),
        .mem_write(mem_write),
        .pc_write(pc_write),
        .branch(branch),
        .jump(jump),
        .alu_src(alu_src),
        .reg_dst(reg_dst),
        .mem_to_reg(mem_to_reg),
        .load_size_control(load_size_control),
        .store_size_control(store_size_control),
        .shift_amt_selector(shift_amt_selector),
        .pc_source(pc_source),
        .pc_write_cond(pc_write_cond),
        .current_state(current_state)
    );
    
    // Gerador de clock
    initial begin
        clk = 0;
        forever #5 clk = ~clk; // Clock de 10ns
    end
    
    // Task para reset
    task do_reset;
        begin
            reset = 1;
            #20;
            reset = 0;
            #10;
        end
    endtask
    
    // Task para esperar ciclos
    task wait_cycles;
        input integer cycles;
        begin
            repeat(cycles) @(posedge clk);
        end
    endtask
    
    // Task para executar instrução
    task execute_instruction;
        input [31:0] instr;
        input [7*8:1] name;
        begin
            $display("Executando %s: %h", name, instr);
            instruction = instr;
            wait_cycles(5); // Espera 5 ciclos para execução completa
        end
    endtask
    
    // Teste principal
    initial begin
        $dumpfile("test_j_type.vcd");
        $dumpvars(0, test_j_type);
        
        $display("=== Iniciando Teste J-type ===");
        
        // Reset inicial
        do_reset();
        
        $display("\n=== Testando Instruções J-type ===");
        
        // Teste J - Jump para linha 12
        // j 12 -> opcode=000010, address=000000000000000000001100 (12)
        execute_instruction(32'b00001000000000000000000000001100, "J");
        
        wait_cycles(3);
        
        // Teste JAL - p/  linha 0, salva PC+4 no reg 31
        // jal 0 -> opcode=000011, address=000000000000000000000000 (0)
        execute_instruction(32'b00001100000000000000000000000000, "JAL");
        
        wait_cycles(5);
        
        $display("\n=== Teste J-type Concluído ===");
        $finish;
    end
    
endmodule

parts_made/test/J-type/test_j_type.vcd
$date
	Mon Jul 14 01:56:47 2025
$end
$version
	Icarus Verilog
$end
$timescale
	1ps
$end
$scope module test_j_type $end
$var wire 2 ! store_size_control [1:0] $end
$var wire 2 " shift_amt_selector [1:0] $end
$var wire 1 # reg_write $end
$var wire 1 $ reg_dst $end
$var wire 1 % pc_write_cond $end
$var wire 1 & pc_write $end
$var wire 2 ' pc_source [1:0] $end
$var wire 1 ( mem_write $end
$var wire 1 ) mem_to_reg $end
$var wire 1 * mem_read $end
$var wire 2 + load_size_control [1:0] $end
$var wire 1 , jump $end
$var wire 5 - current_state [4:0] $end
$var wire 1 . branch $end
$var wire 1 / alu_src $end
$var wire 4 0 alu_op [3:0] $end
$var wire 4 1 alu_control [3:0] $end
$var reg 1 2 clk $end
$var reg 32 3 instruction [31:0] $end
$var reg 1 4 reset $end
$scope module uut $end
$var wire 1 2 clk $end
$var wire 5 5 current_state [4:0] $end
$var wire 1 6 div_zero $end
$var wire 32 7 instruction [31:0] $end
$var wire 1 8 overflow $end
$var wire 1 4 reset $end
$var wire 1 9 zero_flag $end
$var parameter 6 : FUNCT_ADD $end
$var parameter 6 ; FUNCT_AND $end
$var parameter 6 < FUNCT_DIV $end
$var parameter 6 = FUNCT_JR $end
$var parameter 6 > FUNCT_MFHI $end
$var parameter 6 ? FUNCT_MFLO $end
$var parameter 6 @ FUNCT_MULT $end
$var parameter 6 A FUNCT_SLL $end
$var parameter 6 B FUNCT_SLT $end
$var parameter 6 C FUNCT_SRA $end
$var parameter 6 D FUNCT_SUB $end
$var parameter 6 E FUNCT_XCHG $end
$var parameter 6 F OP_ADDI $end
$var parameter 6 G OP_BEQ $end
$var parameter 6 H OP_BNE $end
$var parameter 6 I OP_J $end
$var parameter 6 J OP_JAL $end
$var parameter 6 K OP_LB $end
$var parameter 6 L OP_LUI $end
$var parameter 6 M OP_LW $end
$var parameter 6 N OP_SB $end
$var parameter 6 O OP_SLLM $end
$var parameter 6 P OP_SW $end
$var parameter 6 Q OP_TYPE_R $end
$var parameter 5 R ST_ADD $end
$var parameter 5 S ST_ADDI $end
$var parameter 5 T ST_AND $end
$var parameter 5 U ST_BEQ $end
$var parameter 5 V ST_BNE $end
$var parameter 5 W ST_DECODE $end
$var parameter 5 X ST_DIV $end
$var parameter 5 Y ST_DIV0 $end
$var parameter 5 Z ST_FETCH $end
$var parameter 5 [ ST_J $end
$var parameter 5 \ ST_JAL $end
$var parameter 5 ] ST_JR $end
$var parameter 5 ^ ST_LB $end
$var parameter 5 _ ST_LUI $end
$var parameter 5 ` ST_LW $end
$var parameter 5 a ST_MFHI $end
$var parameter 5 b ST_MFLO $end
$var parameter 5 c ST_MULT $end
$var parameter 5 d ST_OPCODE404 $end
$var parameter 5 e ST_OVERFLOW $end
$var parameter 5 f ST_RESET $end
$var parameter 5 g ST_SB $end
$var parameter 5 h ST_SLL $end
$var parameter 5 i ST_SLLM $end
$var parameter 5 j ST_SLT $end
$var parameter 5 k ST_SRA $end
$var parameter 5 l ST_SUB $end
$var parameter 5 m ST_SW $end
$var parameter 5 n ST_XCHG $end
$var reg 26 o address [25:0] $end
$var reg 4 p alu_control [3:0] $end
$var reg 4 q alu_op [3:0] $end
$var reg 1 r alu_overflow $end
$var reg 1 / alu_src $end
$var reg 1 s alu_zero $end
$var reg 1 . branch $end
$var reg 5 t counter [4:0] $end
$var reg 6 u funct [5:0] $end
$var reg 16 v immediate [15:0] $end
$var reg 1 , jump $end
$var reg 2 w load_size_control [1:0] $end
$var reg 1 * mem_read $end
$var reg 1 ) mem_to_reg $end
$var reg 1 ( mem_write $end
$var reg 6 x opcode [5:0] $end
$var reg 2 y pc_source [1:0] $end
$var reg 1 & pc_write $end
$var reg 1 % pc_write_cond $end
$var reg 5 z rd [4:0] $end
$var reg 1 $ reg_dst $end
$var reg 1 # reg_write $end
$var reg 5 { rs [4:0] $end
$var reg 5 | rt [4:0] $end
$var reg 5 } shamt [4:0] $end
$var reg 2 ~ shift_amt_selector [1:0] $end
$var reg 5 !" state [4:0] $end
$var reg 2 "" store_size_control [1:0] $end
$scope task decode_instruction $end
$upscope $end
$scope task handle_add_state $end
$upscope $end
$scope task handle_addi_state $end
$upscope $end
$scope task handle_and_state $end
$upscope $end
$scope task handle_beq_state $end
$upscope $end
$scope task handle_bne_state $end
$upscope $end
$scope task handle_decode_state $end
$upscope $end
$scope task handle_div0_state $end
$upscope $end
$scope task handle_div_state $end
$upscope $end
$scope task handle_fetch_state $end
$upscope $end
$scope task handle_j_state $end
$upscope $end
$scope task handle_jal_state $end
$upscope $end
$scope task handle_jr_state $end
$upscope $end
$scope task handle_lb_state $end
$upscope $end
$scope task handle_lui_state $end
$upscope $end
$scope task handle_lw_state $end
$upscope $end
$scope task handle_mfhi_state $end
$upscope $end
$scope task handle_mflo_state $end
$upscope $end
$scope task handle_mult_state $end
$upscope $end
$scope task handle_opcode404_state $end
$upscope $end
$scope task handle_overflow_state $end
$upscope $end
$scope task handle_reset_state $end
$upscope $end
$scope task handle_sb_state $end
$upscope $end
$scope task handle_sll_state $end
$upscope $end
$scope task handle_sllm_state $end
$upscope $end
$scope task handle_slt_state $end
$upscope $end
$scope task handle_sra_state $end
$upscope $end
$scope task handle_sub_state $end
$upscope $end
$scope task handle_sw_state $end
$upscope $end
$scope task handle_xchg_state $end
$upscope $end
$scope task reset_control_signals $end
$upscope $end
$upscope $end
$scope task do_reset $end
$upscope $end
$scope task execute_instruction $end
$var reg 32 #" instr [31:0] $end
$var reg 56 $" name [56:1] $end
$upscope $end
$scope task wait_cycles $end
$var integer 32 %" cycles [31:0] $end
$upscope $end
$upscope $end
$enddefinitions $end
$comment Show the parameter values. $end
$dumpall
b1110 n
b10111 m
b1101 l
b1100 k
b1011 j
b10010 i
b1010 h
b10110 g
b0 f
b11010 e
b11011 d
b110 c
b1001 b
b1000 a
b10101 `
b10100 _
b10011 ^
b111 ]
b11001 \
b11000 [
b1 Z
b11100 Y
b101 X
b10 W
b10001 V
b10000 U
b100 T
b1111 S
b11 R
b0 Q
b101011 P
b1 O
b101000 N
b100011 M
b1111 L
b100000 K
b11 J
b10 I
b101 H
b100 G
b1000 F
b101 E
b100010 D
b11 C
b101010 B
b0 A
b11000 @
b10010 ?
b10000 >
b1000 =
b11010 <
b100100 ;
b100000 :
$end
#0
$dumpvars
bx %"
bx $"
bx #"
bx ""
b0 !"
bx ~
bx }
bx |
bx {
bx z
bx y
bx x
bx w
bx v
bx u
bx t
xs
xr
bx q
bx p
bx o
z9
z8
bx 7
z6
b0 5
14
bx 3
02
bx 1
bx 0
x/
x.
b0 -
x,
bx +
x*
x)
x(
bx '
x&
x%
x$
x#
bx "
bx !
$end
#5000
b0 t
12
#10000
02
#15000
12
#20000
02
04
#25000
b1 -
b1 5
b1 !"
0r
0s
b0 1
b0 p
b0 "
b0 ~
b0 '
b0 y
0%
0&
b0 !
b0 ""
b0 +
b0 w
0#
0/
0(
b0 0
b0 q
0)
0*
0.
0,
0$
12
#30000
b1100 o
b1100 v
b1100 u
b0 }
b0 z
b0 |
b0 {
b10 x
02
b101 %"
b1000000000000000000000001100 3
b1000000000000000000000001100 7
b1001010 $"
b1000000000000000000000001100 #"
#35000
b10 -
b10 5
b10 !"
1&
1*
12
#40000
02
#45000
b11000 -
b11000 5
b11000 !"
12
#50000
02
#55000
b1 -
b1 5
b1 !"
b11 '
b11 y
1,
12
#60000
02
#65000
b10 -
b10 5
b10 !"
b0 '
b0 y
1&
1*
0,
12
#70000
02
#75000
b11000 -
b11000 5
b11000 !"
b11 %"
12
#80000
02
#85000
b1 -
b1 5
b1 !"
b11 '
b11 y
1,
12
#90000
02
#95000
b10 -
b10 5
b10 !"
b0 '
b0 y
1&
1*
0,
12
#100000
02
#105000
b0 o
b0 v
b0 u
b11 x
b11000 -
b11000 5
b11000 !"
b101 %"
b1100000000000000000000000000 3
b1100000000000000000000000000 7
b10010100100000101001100 $"
b1100000000000000000000000000 #"
12
#110000
02
#115000
b1 -
b1 5
b1 !"
b11 '
b11 y
1,
12
#120000
02
#125000
b10 -
b10 5
b10 !"
b0 '
b0 y
1&
1*
0,
12
#130000
02
#135000
b11001 -
b11001 5
b11001 !"
12
#140000
02
#145000
b1 -
b1 5
b1 !"
1#
b11 '
b11 y
1,
12
#150000
02
#155000
b10 -
b10 5
b10 !"
b0 '
b0 y
1&
0#
1*
0,
12
#160000
02
#165000
b11001 -
b11001 5
b11001 !"
12
#170000
02
#175000
b1 -
b1 5
b1 !"
1#
b11 '
b11 y
1,
12
#180000
02
#185000
b10 -
b10 5
b10 !"
b0 '
b0 y
1&
0#
1*
0,
12
#190000
02
#195000
b11001 -
b11001 5
b11001 !"
12
#200000
02
#205000
b1 -
b1 5
b1 !"
1#
b11 '
b11 y
1,
12
